Workbook

Sheet Sheet0
A1: Awd_ID | B1: Awd_Title | C1: Q1.1. What type of award is your ATE grant? - Selected Choice | D1: Q1.1. What type of award is your ATE grant? - Other type of award (describe) - Text | E1: Q1.2. Was 2023 the first year of your current grant? | F1: Q1.2.1 Is your current grant a continuation of a previous ATE project? | G1: Q.1.3. Does your grant have any co-principal investigators (co-PIs)? | H1: Q1.4. At what type of institution is the PI for this project located? - Selected Choice | I1: Q1.4. At what type of institution is the PI for this project located? - Other (describe) - Text | J1: Q1.4.1. Is this institution designated as a minority-serving institution as defined in US law under Title III of the Higher Education Act of 1965? | K1: Q1.4.1.a. Which designation does your institution hold? - Hispanic-serving institution | L1: Q1.4.1.a. Which designation does your institution hold? - Historically black college or university | M1: Q1.4.1.a. Which designation does your institution hold? - Predominately black institution | N1: Q1.4.1.a. Which designation does your institution hold? - Tribal college or university | O1: Q1.4.1.a. Which designation does your institution hold? - Asian American and Native American Pacific Islander-serving institution | P1: Q1.4.1.a. Which designation does your institution hold? - Alaska native-serving institution and Native Hawaiian-serving institution | Q1: Q1.4.1.a. Which designation does your institution hold? - Native American-serving Nontribal institution | R1: Q1.4.1.a. Which designation does your institution hold? - Other (describe) | S1: Q1.4.1.a. Which designation does your institution hold? - Other (describe) - Text | U1: Q1.5. Project website: | V1: Q1.6. How many years does your grant cover? | W1: Q1.7. What is the total value of the grant? (Use a numeric response. Do not use a symbol, such as a dollar sign "$") | X1: Q1.8. Which of the following best represents the primary disciplinary focus of your ATE project? - Selected Choice | Y1: Q1.8. Which of the following best represents the primary disciplinary focus of your ATE project? - Other Advanced Manufacturing Technologies (please specify): - Text | Z1: Q1.8. Which of the following best represents the primary disciplinary focus of your ATE project? - Other Agricultural and Environmental Technologies (please specify): - Text | AA1: Q1.8. Which of the following best represents the primary disciplinary focus of your ATE project? - Other Bio and Chemical Technologies (please specify): - Text | AB1: Q1.8. Which of the following best represents the primary disciplinary focus of your ATE project? - Other Engineering Technologies (please specify): - Text | AC1: Q1.8. Which of the following best represents the primary disciplinary focus of your ATE project? - Other Information and Securities Technologies (please specify): - Text | AD1: Q1.8. Which of the following best represents the primary disciplinary focus of your ATE project? - Other General or Interdisciplinary/Cross-Cutting Advanced Technological Education (please specify): - Text | AE1: Q1.8. Which of the following best represents the primary disciplinary focus of your ATE project? - Other (please specify): - Text | AF1: Recode Discipline | AG1: Q1.9. Does your ATE project have a secondary disciplinary focus you would like to report? | AH1: Q1.9.1. Which of the following best represents the secondary disciplinary focus of your ATE project? - Selected Choice | AI1: Q1.9.1. Which of the following best represents the secondary disciplinary focus of your ATE project? - Other Advanced Manufacturing Technologies (please specify): - Text | AJ1: Q1.9.1. Which of the following best represents the secondary disciplinary focus of your ATE project? - Other Agricultural and Environmental Technologies (please specify): - Text | AK1: Q1.9.1. Which of the following best represents the secondary disciplinary focus of your ATE project? - Other Bio and Chemical Technologies (please specify): - Text | AL1: Q1.9.1. Which of the following best represents the secondary disciplinary focus of your ATE project? - Other Engineering Technologies (please specify): - Text | AM1: Q1.9.1. Which of the following best represents the secondary disciplinary focus of your ATE project? - Other Information and Securities Technologies (please specify): - Text | AN1: Q1.9.1. Which of the following best represents the secondary disciplinary focus of your ATE project? - Other General or Interdisciplinary/Cross-Cutting Advanced Technological Education (please specify): - Text | AO1: Q1.9.1. Which of the following best represents the secondary disciplinary focus of your ATE project? - Other (please specify): - Text | AP1: Recode Secondary Discipline | AQ1: Q1.10. Does your project engage in any type of student recruitment? | AR1: Q1.10.1. How challenging is it to recruit students to participate in your project? | AS1: Q1.10.2. Does your project explicitly aim to engage or recruit students from the following groups? - Women | AT1: Q1.10.2. Does your project explicitly aim to engage or recruit students from the following groups? - Underrepresented racial or ethnic minorities | AU1: Q1.10.2. Does your project explicitly aim to engage or recruit students from the following groups? - Veterans | AV1: Q1.10.2. Does your project explicitly aim to engage or recruit students from the following groups? - First-generation college students | AW1: Q1.10.2. Does your project explicitly aim to engage or recruit students from the following groups? - Low-income students | AX1: Q1.10.2. Does your project explicitly aim to engage or recruit students from the following groups? - Individuals from rural areas | AY1: Q1.10.2. Does your project explicitly aim to engage or recruit students from the following groups? - Persons with disabilities | AZ1: Q1.10.2. Does your project explicitly aim to engage or recruit students from the following groups? - Dislocated workers (i.e., persons terminated as a result of workplace closure) | BA1: Q1.11. How does the PI identify their ethnicity? | BB1: Q1.12. How does the PI identify their race? - Selected Choice | BC1: Q1.12. How does the PI identify their race? - Identity not listed (describe) - Text | BD1: Recode: Race and Ethnicity | BE1: Q1.13. How does the PI identify their gender? - Selected Choice | BF1: Q1.13. How does the PI identify their gender? - Identity not listed (describe) - Text | BG1: Q1.14. What is the PIs age? | BH1: Program Development Program Development is the creation or substantial modification of a specific degree or certification program for implementation at specific colleges or high schools. Do not use this section of the survey to report on: Curricula developed only for use by other institutions. Workshops to build capacity around program development or implementation. In 2023, did your ATE project create or substantially modify an academic degree or certificate program? | BI1: Q2.1. How many degree or certificate programs were created or modified by your ATE project in 2023? (If you have more than five programs, please contact Erika at atesurvey@evalu-ate.org.) | BJ1: Q2.2 - What is the name of the degree or certificate program? - Program 1 - | BK1: Q2.2 - What is the name of the degree or certificate program? - Program 2 - | BL1: Q2.2 - What is the name of the degree or certificate program? - Program 3 - | BM1: Q2.2 - What is the name of the degree or certificate program? - Program 4 - | BN1: Q2.2 - What is the name of the degree or certificate program? - Program 5 - | BO1: Q2.2 - Which type of credential is awarded by this program? - Program 1 | BP1: Q2.2 - Which type of credential is awarded by this program? - Program 2 | BQ1: Q2.2 - Which type of credential is awarded by this program? - Program 3 | BR1: Q2.2 - Which type of credential is awarded by this program? - Program 4 | BS1: Q2.2 - Which type of credential is awarded by this program? - Program 5 | BT1: Q2.2.1. Which of the following best describes the main audience for this certificate, [QID34%231-ChoiceTextEntryValue-1-1]? - Selected Choice | BU1: Q2.2.1. Which of the following best describes the main audience for this certificate, [QID34%231-ChoiceTextEntryValue-1-1]? - Other (describe) - Text | BV1: Q2.2.1. Which of the following best describes the main audience for this certificate, [QID34%231-ChoiceTextEntryValue-2-1]? - Selected Choice | BW1: Q2.2.1. Which of the following best describes the main audience for this certificate, [QID34%231-ChoiceTextEntryValue-2-1]? - Other (describe) - Text | BX1: Q2.2.1. Which of the following best describes the main audience for this certificate, [QID34%231-ChoiceTextEntryValue-3-1]? - Selected Choice | BY1: Q2.2.1. Which of the following best describes the main audience for this certificate, [QID34%231-ChoiceTextEntryValue-3-1]? - Other (describe) - Text | BZ1: Q2.2.1. Which of the following best describes the main audience for this certificate, [QID34%231-ChoiceTextEntryValue-4-1]? - Selected Choice | CA1: Q2.2.1. Which of the following best describes the main audience for this certificate, [QID34%231-ChoiceTextEntryValue-4-1]? - Other (describe) - Text | CB1: Q2.2.1. Which of the following best describes the main audience for this certificate, [QID34%231-ChoiceTextEntryValue-5-1]? - Selected Choice | CC1: Q2.2.1. Which of the following best describes the main audience for this certificate, [QID34%231-ChoiceTextEntryValue-5-1]? - Other (describe) - Text | CD1: Q2.3. How many students took at least one course in each certificate or degree program? (If no st... - Total number of students - [QID34%231-ChoiceTextEntryValue-1-1] - | CE1: Q2.3. How many students took at least one course in each certificate or degree program? (If no st... - Total number of students - [QID34%231-ChoiceTextEntryValue-2-1] - | CF1: Q2.3. How many students took at least one course in each certificate or degree program? (If no st... - Total number of students - [QID34%231-ChoiceTextEntryValue-3-1] - | CG1: Q2.3. How many students took at least one course in each certificate or degree program? (If no st... - Total number of students - [QID34%231-ChoiceTextEntryValue-4-1] - | CH1: Q2.3. How many students took at least one course in each certificate or degree program? (If no st... - Total number of students - [QID34%231-ChoiceTextEntryValue-5-1] - | CI1: Q2.4. How many students from each of the following demographic categories participated in [QID34%231-ChoiceTextEntryValue-1-1] in 2023? (Please make sure your total number of students matches your responses in Q2.3) - American Indian or Alaska Native - [QID34%231-ChoiceTextEntryValue-1-1] | CJ1: Q2.4. How many students from each of the following demographic categories participated in [QID34%231-ChoiceTextEntryValue-1-1] in 2023? (Please make sure your total number of students matches your responses in Q2.3) - Asian - [QID34%231-ChoiceTextEntryValue-1-1] | CK1: Q2.4. How many students from each of the following demographic categories participated in [QID34%231-ChoiceTextEntryValue-1-1] in 2023? (Please make sure your total number of students matches your responses in Q2.3) - Black or African American - [QID34%231-ChoiceTextEntryValue-1-1] | CL1: Q2.4. How many students from each of the following demographic categories participated in [QID34%231-ChoiceTextEntryValue-1-1] in 2023? (Please make sure your total number of students matches your responses in Q2.3) - Hispanic or Latino/Latina - [QID34%231-ChoiceTextEntryValue-1-1] | CM1: Q2.4. How many students from each of the following demographic categories participated in [QID34%231-ChoiceTextEntryValue-1-1] in 2023? (Please make sure your total number of students matches your responses in Q2.3) - Multiracial or Multiethnic - [QID34%231-ChoiceTextEntryValue-1-1] | CN1: Q2.4. How many students from each of the following demographic categories participated in [QID34%231-ChoiceTextEntryValue-1-1] in 2023? (Please make sure your total number of students matches your responses in Q2.3) - Native Hawaiian or other Pacific Islander - [QID34%231-ChoiceTextEntryValue-1-1] | CO1: Q2.4. How many students from each of the following demographic categories participated in [QID34%231-ChoiceTextEntryValue-1-1] in 2023? (Please make sure your total number of students matches your responses in Q2.3) - White - [QID34%231-ChoiceTextEntryValue-1-1] | CP1: Q2.4. How many students from each of the following demographic categories participated in [QID34%231-ChoiceTextEntryValue-1-1] in 2023? (Please make sure your total number of students matches your responses in Q2.3) - Racial or Ethnic Identity Unknown (e.g. student refused; data not captured... - Racial or Ethnic Identity Unknown (e.g. student refused; data not captured by program) - [QID34%231-ChoiceTextEntryValue-1-1] | CQ1: Q2.5. How many students of each of the following gender categories participated in [QID34%231-ChoiceTextEntryValue-1-1] in 2023? (Please make sure your total number of students matches your responses in Q2.3) - Men - [QID34%231-ChoiceTextEntryValue-1-1] | CR1: Q2.5. How many students of each of the following gender categories participated in [QID34%231-ChoiceTextEntryValue-1-1] in 2023? (Please make sure your total number of students matches your responses in Q2.3) - Women - [QID34%231-ChoiceTextEntryValue-1-1] | CS1: Q2.5. How many students of each of the following gender categories participated in [QID34%231-ChoiceTextEntryValue-1-1] in 2023? (Please make sure your total number of students matches your responses in Q2.3) - Other Gender Identities - [QID34%231-ChoiceTextEntryValue-1-1] | CT1: Q2.5. How many students of each of the following gender categories participated in [QID34%231-ChoiceTextEntryValue-1-1] in 2023? (Please make sure your total number of students matches your responses in Q2.3) - Gender Identity Unknown (e.g. student refused; data not captured by program... - Gender Identity Unknown (e.g. student refused; data not captured by program) - [QID34%231-ChoiceTextEntryValue-1-1] | CU1: Q2.6. How many students in [QID34%231-ChoiceTextEntryValue-1-1] requested accommodations under the Americans with Disabilities Act in 2023? | CV1: Q2.4. How many students from each of the following demographic categories participated in [QID34%231-ChoiceTextEntryValue-2-1] in 2023? (Please make sure your total number of students matches your responses in Q2.3) - American Indian or Alaska Native - [QID34%231-ChoiceTextEntryValue-2-1] | CW1: Q2.4. How many students from each of the following demographic categories participated in [QID34%231-ChoiceTextEntryValue-2-1] in 2023? (Please make sure your total number of students matches your responses in Q2.3) - Asian - [QID34%231-ChoiceTextEntryValue-2-1] | CX1: Q2.4. How many students from each of the following demographic categories participated in [QID34%231-ChoiceTextEntryValue-2-1] in 2023? (Please make sure your total number of students matches your responses in Q2.3) - Black or African American - [QID34%231-ChoiceTextEntryValue-2-1] | CY1: Q2.4. How many students from each of the following demographic categories participated in [QID34%231-ChoiceTextEntryValue-2-1] in 2023? (Please make sure your total number of students matches your responses in Q2.3) - Hispanic or Latino/Latina - [QID34%231-ChoiceTextEntryValue-2-1] | CZ1: Q2.4. How many students from each of the following demographic categories participated in [QID34%231-ChoiceTextEntryValue-2-1] in 2023? (Please make sure your total number of students matches your responses in Q2.3) - Multiracial or Multiethnic - [QID34%231-ChoiceTextEntryValue-2-1] | DA1: Q2.4. How many students from each of the following demographic categories participated in [QID34%231-ChoiceTextEntryValue-2-1] in 2023? (Please make sure your total number of students matches your responses in Q2.3) - Native Hawaiian or other Pacific Islander - [QID34%231-ChoiceTextEntryValue-2-1] | DB1: Q2.4. How many students from each of the following demographic categories participated in [QID34%231-ChoiceTextEntryValue-2-1] in 2023? (Please make sure your total number of students matches your responses in Q2.3) - White - [QID34%231-ChoiceTextEntryValue-2-1] | DC1: Q2.4. How many students from each of the following demographic categories participated in [QID34%231-ChoiceTextEntryValue-2-1] in 2023? (Please make sure your total number of students matches your responses in Q2.3) - Racial or Ethnic Identity Unknown (e.g. student refused; data not captured... - Racial or Ethnic Identity Unknown (e.g. student refused; data not captured by program) - [QID34%231-ChoiceTextEntryValue-2-1] | DD1: Q2.5. How many students of each of the following gender categories participated in [QID34%231-ChoiceTextEntryValue-2-1] in 2023? (Please make sure your total number of students matches your responses in Q2.3) - Men - [QID34%231-ChoiceTextEntryValue-2-1] | DE1: Q2.5. How many students of each of the following gender categories participated in [QID34%231-ChoiceTextEntryValue-2-1] in 2023? (Please make sure your total number of students matches your responses in Q2.3) - Women - [QID34%231-ChoiceTextEntryValue-2-1] | DF1: Q2.5. How many students of each of the following gender categories participated in [QID34%231-ChoiceTextEntryValue-2-1] in 2023? (Please make sure your total number of students matches your responses in Q2.3) - Other Gender Identities - [QID34%231-ChoiceTextEntryValue-2-1] | DG1: Q2.5. How many students of each of the following gender categories participated in [QID34%231-ChoiceTextEntryValue-2-1] in 2023? (Please make sure your total number of students matches your responses in Q2.3) - Gender Identity Unknown (e.g. student refused; data not captured by program... - Gender Identity Unknown (e.g. student refused; data not captured by program) - [QID34%231-ChoiceTextEntryValue-2-1] | DH1: Q2.6. How many students in [QID34%231-ChoiceTextEntryValue-2-1] requested accommodations under the Americans with Disabilities Act in 2023? | DI1: Q2.4. How many students from each of the following demographic categories participated in [QID34%231-ChoiceTextEntryValue-3-1] in 2023? (Please make sure your total number of students matches your responses in Q2.3) - American Indian or Alaska Native - [QID34%231-ChoiceTextEntryValue-3-1] | DJ1: Q2.4. How many students from each of the following demographic categories participated in [QID34%231-ChoiceTextEntryValue-3-1] in 2023? (Please make sure your total number of students matches your responses in Q2.3) - Asian - [QID34%231-ChoiceTextEntryValue-3-1] | DK1: Q2.4. How many students from each of the following demographic categories participated in [QID34%231-ChoiceTextEntryValue-3-1] in 2023? (Please make sure your total number of students matches your responses in Q2.3) - Black or African American - [QID34%231-ChoiceTextEntryValue-3-1] | DL1: Q2.4. How many students from each of the following demographic categories participated in [QID34%231-ChoiceTextEntryValue-3-1] in 2023? (Please make sure your total number of students matches your responses in Q2.3) - Hispanic or Latino/Latina - [QID34%231-ChoiceTextEntryValue-3-1] | DM1: Q2.4. How many students from each of the following demographic categories participated in [QID34%231-ChoiceTextEntryValue-3-1] in 2023? (Please make sure your total number of students matches your responses in Q2.3) - Multiracial or Multiethnic - [QID34%231-ChoiceTextEntryValue-3-1] | DN1: Q2.4. How many students from each of the following demographic categories participated in [QID34%231-ChoiceTextEntryValue-3-1] in 2023? (Please make sure your total number of students matches your responses in Q2.3) - Native Hawaiian or other Pacific Islander - [QID34%231-ChoiceTextEntryValue-3-1] | DO1: Q2.4. How many students from each of the following demographic categories participated in [QID34%231-ChoiceTextEntryValue-3-1] in 2023? (Please make sure your total number of students matches your responses in Q2.3) - White - [QID34%231-ChoiceTextEntryValue-3-1] | DP1: Q2.4. How many students from each of the following demographic categories participated in [QID34%231-ChoiceTextEntryValue-3-1] in 2023? (Please make sure your total number of students matches your responses in Q2.3) - Racial or Ethnic Identity Unknown (e.g. student refused; data not captured... - Racial or Ethnic Identity Unknown (e.g. student refused; data not captured by program) - [QID34%231-ChoiceTextEntryValue-3-1] | DQ1: Q2.5. How many students of each of the following gender categories participated in [QID34%231-ChoiceTextEntryValue-3-1] in 2023? (Please make sure your total number of students matches your responses in Q2.3) - Men - [QID34%231-ChoiceTextEntryValue-3-1] | DR1: Q2.5. How many students of each of the following gender categories participated in [QID34%231-ChoiceTextEntryValue-3-1] in 2023? (Please make sure your total number of students matches your responses in Q2.3) - Women - [QID34%231-ChoiceTextEntryValue-3-1] | DS1: Q2.5. How many students of each of the following gender categories participated in [QID34%231-ChoiceTextEntryValue-3-1] in 2023? (Please make sure your total number of students matches your responses in Q2.3) - Other Gender Identities - [QID34%231-ChoiceTextEntryValue-3-1] | DT1: Q2.5. How many students of each of the following gender categories participated in [QID34%231-ChoiceTextEntryValue-3-1] in 2023? (Please make sure your total number of students matches your responses in Q2.3) - Gender Identity Unknown (e.g. student refused; data not captured by program... - Gender Identity Unknown (e.g. student refused; data not captured by program) - [QID34%231-ChoiceTextEntryValue-3-1] | DU1: Q2.6. How many students in [QID34%231-ChoiceTextEntryValue-3-1] requested accommodations under the Americans with Disabilities Act in 2023? | DV1: Q2.4. How many students from each of the following demographic categories participated in [QID34%231-ChoiceTextEntryValue-4-1] in 2023? (Please make sure your total number of students matches your responses in Q2.3) - American Indian or Alaska Native - [QID34%231-ChoiceTextEntryValue-4-1] | DW1: Q2.4. How many students from each of the following demographic categories participated in [QID34%231-ChoiceTextEntryValue-4-1] in 2023? (Please make sure your total number of students matches your responses in Q2.3) - Asian - [QID34%231-ChoiceTextEntryValue-4-1] | DX1: Q2.4. How many students from each of the following demographic categories participated in [QID34%231-ChoiceTextEntryValue-4-1] in 2023? (Please make sure your total number of students matches your responses in Q2.3) - Black or African American - [QID34%231-ChoiceTextEntryValue-4-1] | DY1: Q2.4. How many students from each of the following demographic categories participated in [QID34%231-ChoiceTextEntryValue-4-1] in 2023? (Please make sure your total number of students matches your responses in Q2.3) - Hispanic or Latino/Latina - [QID34%231-ChoiceTextEntryValue-4-1] | DZ1: Q2.4. How many students from each of the following demographic categories participated in [QID34%231-ChoiceTextEntryValue-4-1] in 2023? (Please make sure your total number of students matches your responses in Q2.3) - Multiracial or Multiethnic - [QID34%231-ChoiceTextEntryValue-4-1] | EA1: Q2.4. How many students from each of the following demographic categories participated in [QID34%231-ChoiceTextEntryValue-4-1] in 2023? (Please make sure your total number of students matches your responses in Q2.3) - Native Hawaiian or other Pacific Islander - [QID34%231-ChoiceTextEntryValue-4-1] | EB1: Q2.4. How many students from each of the following demographic categories participated in [QID34%231-ChoiceTextEntryValue-4-1] in 2023? (Please make sure your total number of students matches your responses in Q2.3) - White - [QID34%231-ChoiceTextEntryValue-4-1] | EC1: Q2.4. How many students from each of the following demographic categories participated in [QID34%231-ChoiceTextEntryValue-4-1] in 2023? (Please make sure your total number of students matches your responses in Q2.3) - Racial or Ethnic Identity Unknown (e.g. student refused; data not captured... - Racial or Ethnic Identity Unknown (e.g. student refused; data not captured by program) - [QID34%231-ChoiceTextEntryValue-4-1] | ED1: Q2.5. How many students of each of the following gender categories participated in [QID34%231-ChoiceTextEntryValue-4-1] in 2023? (Please make sure your total number of students matches your responses in Q2.3) - Men - [QID34%231-ChoiceTextEntryValue-4-1] | EE1: Q2.5. How many students of each of the following gender categories participated in [QID34%231-ChoiceTextEntryValue-4-1] in 2023? (Please make sure your total number of students matches your responses in Q2.3) - Women - [QID34%231-ChoiceTextEntryValue-4-1] | EF1: Q2.5. How many students of each of the following gender categories participated in [QID34%231-ChoiceTextEntryValue-4-1] in 2023? (Please make sure your total number of students matches your responses in Q2.3) - Other Gender Identities - [QID34%231-ChoiceTextEntryValue-4-1] | EG1: Q2.5. How many students of each of the following gender categories participated in [QID34%231-ChoiceTextEntryValue-4-1] in 2023? (Please make sure your total number of students matches your responses in Q2.3) - Gender Identity Unknown (e.g. student refused; data not captured by program... - Gender Identity Unknown (e.g. student refused; data not captured by program) - [QID34%231-ChoiceTextEntryValue-4-1] | EH1: Q2.6. How many students in [QID34%231-ChoiceTextEntryValue-4-1] requested accommodations under the Americans with Disabilities Act in 2023? | EI1: Q2.4. How many students from each of the following demographic categories participated in [QID34%231-ChoiceTextEntryValue-5-1] in 2023? (Please make sure your total number of students matches your responses in Q2.3) - American Indian or Alaska Native - [QID34%231-ChoiceTextEntryValue-5-1] | EJ1: Q2.4. How many students from each of the following demographic categories participated in [QID34%231-ChoiceTextEntryValue-5-1] in 2023? (Please make sure your total number of students matches your responses in Q2.3) - Asian - [QID34%231-ChoiceTextEntryValue-5-1] | EK1: Q2.4. How many students from each of the following demographic categories participated in [QID34%231-ChoiceTextEntryValue-5-1] in 2023? (Please make sure your total number of students matches your responses in Q2.3) - Black or African American - [QID34%231-ChoiceTextEntryValue-5-1] | EL1: Q2.4. How many students from each of the following demographic categories participated in [QID34%231-ChoiceTextEntryValue-5-1] in 2023? (Please make sure your total number of students matches your responses in Q2.3) - Hispanic or Latino/Latina - [QID34%231-ChoiceTextEntryValue-5-1] | EM1: Q2.4. How many students from each of the following demographic categories participated in [QID34%231-ChoiceTextEntryValue-5-1] in 2023? (Please make sure your total number of students matches your responses in Q2.3) - Multiracial or Multiethnic - [QID34%231-ChoiceTextEntryValue-5-1] | EN1: Q2.4. How many students from each of the following demographic categories participated in [QID34%231-ChoiceTextEntryValue-5-1] in 2023? (Please make sure your total number of students matches your responses in Q2.3) - Native Hawaiian or other Pacific Islander - [QID34%231-ChoiceTextEntryValue-5-1] | EO1: Q2.4. How many students from each of the following demographic categories participated in [QID34%231-ChoiceTextEntryValue-5-1] in 2023? (Please make sure your total number of students matches your responses in Q2.3) - White - [QID34%231-ChoiceTextEntryValue-5-1] | EP1: Q2.4. How many students from each of the following demographic categories participated in [QID34%231-ChoiceTextEntryValue-5-1] in 2023? (Please make sure your total number of students matches your responses in Q2.3) - Racial or Ethnic Identity Unknown (e.g. student refused; data not captured... - Racial or Ethnic Identity Unknown (e.g. student refused; data not captured by program) - [QID34%231-ChoiceTextEntryValue-5-1] | EQ1: Q2.5. How many students of each of the following gender categories participated in [QID34%231-ChoiceTextEntryValue-5-1] in 2023? (Please make sure your total number of students matches your responses in Q2.3) - Men - [QID34%231-ChoiceTextEntryValue-5-1] | ER1: Q2.5. How many students of each of the following gender categories participated in [QID34%231-ChoiceTextEntryValue-5-1] in 2023? (Please make sure your total number of students matches your responses in Q2.3) - Women - [QID34%231-ChoiceTextEntryValue-5-1] | ES1: Q2.5. How many students of each of the following gender categories participated in [QID34%231-ChoiceTextEntryValue-5-1] in 2023? (Please make sure your total number of students matches your responses in Q2.3) - Other Gender Identities - [QID34%231-ChoiceTextEntryValue-5-1] | ET1: Q2.5. How many students of each of the following gender categories participated in [QID34%231-ChoiceTextEntryValue-5-1] in 2023? (Please make sure your total number of students matches your responses in Q2.3) - Gender Identity Unknown (e.g. student refused; data not captured by program... - Gender Identity Unknown (e.g. student refused; data not captured by program) - [QID34%231-ChoiceTextEntryValue-5-1] | EU1: Q2.6. How many students in [QID34%231-ChoiceTextEntryValue-5-1] requested accommodations under the Americans with Disabilities Act in 2023? | EV1: Q2.7. Did any students complete the following program(s) in 2023? - [QID34%231-ChoiceTextEntryValue-1-1] | EW1: Q2.7. Did any students complete the following program(s) in 2023? - [QID34%231-ChoiceTextEntryValue-2-1] | EX1: Q2.7. Did any students complete the following program(s) in 2023? - [QID34%231-ChoiceTextEntryValue-3-1] | EY1: Q2.7. Did any students complete the following program(s) in 2023? - [QID34%231-ChoiceTextEntryValue-4-1] | EZ1: Q2.7. Did any students complete the following program(s) in 2023? - [QID34%231-ChoiceTextEntryValue-5-1] | FA1: Q2.7.1. How many students completed each of the following program(s) in 2023? - [QID34%231-ChoiceTextEntryValue-1-1] | FB1: Q2.7.1. How many students completed each of the following program(s) in 2023? - [QID34%231-ChoiceTextEntryValue-2-1] | FC1: Q2.7.1. How many students completed each of the following program(s) in 2023? - [QID34%231-ChoiceTextEntryValue-3-1] | FD1: Q2.7.1. How many students completed each of the following program(s) in 2023? - [QID34%231-ChoiceTextEntryValue-4-1] | FE1: Q2.7.1. How many students completed each of the following program(s) in 2023? - [QID34%231-ChoiceTextEntryValue-5-1] | FF1: Q2.7.2. How does your project or institution define a student's "completion" of a program? | FG1: Q2.8. How many students across all programs listed are veterans or first generation to attend college? If you have not collected this data for 2023, you do not need to respond to this question. - Veterans - Total number of students | FH1: Q2.8. How many students across all programs listed are veterans or first generation to attend college? If you have not collected this data for 2023, you do not need to respond to this question. - First generation to attend college - Total number of students | FI1: Course Development Course development is the creation or substantial modification of sequenced, intentional learning experiences for students at specific colleges or high schools. Do not use this section of the survey to report on: Course curricula developed only for use by other institutions Workshops to build capacity around program development or implementation In 2023, did your ATE project create or substantially modify an academic course? (This course does not need to be associated with the development of an academic program.) | FJ1: Q2.9. How many courses were created or modified by your ATE project in 2023? | FK1: Q2.10. - What is the name of the course? - Course 1 - | FL1: Q2.10. - What is the name of the course? - Course 2 - | FM1: Q2.10. - What is the name of the course? - Course 3 - | FN1: Q2.10. - What is the name of the course? - Course 4 - | FO1: Q2.10. - What is the name of the course? - Course 5 - | FP1: Q2.10. - What is the name of the course? - Course 6 - | FQ1: Q2.10. - What is the name of the course? - Course 7 - | FR1: Q2.10. - What is the name of the course? - Course 8 - | FS1: Q2.10. - What is the name of the course? - Course 9 - | FT1: Q2.10. - What is the name of the course? - Course 10 - | FU1: Q2.10. - What is the name of the course? - Course 11 - | FV1: Q2.10. - What is the name of the course? - Course 12 - | FW1: Q2.10. - What is the name of the course? - Course 13 - | FX1: Q2.10. - What is the name of the course? - Course 14 - | FY1: Q2.10. - What is the name of the course? - Course 15 - | FZ1: Q2.10. - What is the name of the course? - Course 16 - | GA1: Q2.10. - What is the name of the course? - Course 17 - | GB1: Q2.10. - What is the name of the course? - Course 18 - | GC1: Q2.10. - What is the name of the course? - Course 19 - | GD1: Q2.10. - What is the name of the course? - Course 20 - | GE1: Q2.10. - Which of the following best describes the main audience for this course? - Course 1 | GF1: Q2.10. - Which of the following best describes the main audience for this course? - Course 2 | GG1: Q2.10. - Which of the following best describes the main audience for this course? - Course 3 | GH1: Q2.10. - Which of the following best describes the main audience for this course? - Course 4 | GI1: Q2.10. - Which of the following best describes the main audience for this course? - Course 5 | GJ1: Q2.10. - Which of the following best describes the main audience for this course? - Course 6 | GK1: Q2.10. - Which of the following best describes the main audience for this course? - Course 7 | GL1: Q2.10. - Which of the following best describes the main audience for this course? - Course 8 | GM1: Q2.10. - Which of the following best describes the main audience for this course? - Course 9 | GN1: Q2.10. - Which of the following best describes the main audience for this course? - Course 10 | GO1: Q2.10. - Which of the following best describes the main audience for this course? - Course 11 | GP1: Q2.10. - Which of the following best describes the main audience for this course? - Course 12 | GQ1: Q2.10. - Which of the following best describes the main audience for this course? - Course 13 | GR1: Q2.10. - Which of the following best describes the main audience for this course? - Course 14 | GS1: Q2.10. - Which of the following best describes the main audience for this course? - Course 15 | GT1: Q2.10. - Which of the following best describes the main audience for this course? - Course 16 | GU1: Q2.10. - Which of the following best describes the main audience for this course? - Course 17 | GV1: Q2.10. - Which of the following best describes the main audience for this course? - Course 18 | GW1: Q2.10. - Which of the following best describes the main audience for this course? - Course 19 | GX1: Q2.10. - Which of the following best describes the main audience for this course? - Course 20 | GY1: Q2.10. - Was this course offered in 2023? - Course 1 | GZ1: Q2.10. - Was this course offered in 2023? - Course 2 | HA1: Q2.10. - Was this course offered in 2023? - Course 3 | HB1: Q2.10. - Was this course offered in 2023? - Course 4 | HC1: Q2.10. - Was this course offered in 2023? - Course 5 | HD1: Q2.10. - Was this course offered in 2023? - Course 6 | HE1: Q2.10. - Was this course offered in 2023? - Course 7 | HF1: Q2.10. - Was this course offered in 2023? - Course 8 | HG1: Q2.10. - Was this course offered in 2023? - Course 9 | HH1: Q2.10. - Was this course offered in 2023? - Course 10 | HI1: Q2.10. - Was this course offered in 2023? - Course 11 | HJ1: Q2.10. - Was this course offered in 2023? - Course 12 | HK1: Q2.10. - Was this course offered in 2023? - Course 13 | HL1: Q2.10. - Was this course offered in 2023? - Course 14 | HM1: Q2.10. - Was this course offered in 2023? - Course 15 | HN1: Q2.10. - Was this course offered in 2023? - Course 16 | HO1: Q2.10. - Was this course offered in 2023? - Course 17 | HP1: Q2.10. - Was this course offered in 2023? - Course 18 | HQ1: Q2.10. - Was this course offered in 2023? - Course 19 | HR1: Q2.10. - Was this course offered in 2023? - Course 20 | HS1: Q2.10.1 How many students completed this course in 2023? - [QID62%231-ChoiceTextEntryValue-1-1] - Number of Students | HT1: Q2.10.1. How many students completed this course in 2023? - [QID62%231-ChoiceTextEntryValue-2-1] - Number of Students | HU1: Q2.10.1 How many students completed this course in 2023? - [QID62%231-ChoiceTextEntryValue-3-1] - Number of Students | HV1: Q2.10.1. How many students completed this course in 2023? - [QID62%231-ChoiceTextEntryValue-4-1] - Number of Students | HW1: Q2.10.1. How many students completed this course in 2023? - [QID62%231-ChoiceTextEntryValue-5-1] - Number of Students | HX1: Q2.10.1. How many students completed this course in 2023? - [QID62%231-ChoiceTextEntryValue-6-1] - Number of Students | HY1: Q2.10.1. How many students completed this course in 2023? - [QID62%231-ChoiceTextEntryValue-7-1] - Number of Students | HZ1: Q2.10.1. How many students completed this course in 2023? - [QID62%231-ChoiceTextEntryValue-8-1] - Number of Students | IA1: Q2.10.1. How many students completed this course in 2023? - [QID62%231-ChoiceTextEntryValue-9-1] - Number of Students | IB1: Q2.10.1. How many students completed this course in 2023? - [QID62%231-ChoiceTextEntryValue-10-1] - Number of Students | IC1: Q2.10.1. How many students completed this course in 2023? - [QID62%231-ChoiceTextEntryValue-11-1] - Number of Students | ID1: Q2.10.1. How many students completed this course in 2023? - [QID62%231-ChoiceTextEntryValue-12-1] - Number of Students | IE1: Q2.10.1. How many students completed this course in 2023? - [QID62%231-ChoiceTextEntryValue-13-1] - Number of Students | IF1: Q2.10.1. How many students completed this course in 2023? - [QID62%231-ChoiceTextEntryValue-14-1] - Number of Students | IG1: Q2.10.1. How many students completed this course in 2023? - [QID62%231-ChoiceTextEntryValue-15-1] - Number of Students | IH1: Q2.10.1. How many students completed this course in 2023? - [QID62%231-ChoiceTextEntryValue-16-1] - Number of Students | II1: Q2.10.1. How many students completed this course in 2023? - [QID62%231-ChoiceTextEntryValue-17-1] - Number of Students | IJ1: Q2.10.1. How many students completed this course in 2023? - [QID62%231-ChoiceTextEntryValue-18-1] - Number of Students | IK1: Q2.10.1. How many students completed this course in 2023? - [QID62%231-ChoiceTextEntryValue-19-1] - Number of Students | IL1: Q2.10.1. How many students completed this course in 2023? - [QID62%231-ChoiceTextEntryValue-20-1] - Number of Students | IM1: Q2.11. What was the primary delivery mode for the course(s) in 2023? - [QID62%231-ChoiceTextEntryValue-1-1] | IN1: Q2.11. What was the primary delivery mode for the course(s) in 2023? - [QID62%231-ChoiceTextEntryValue-2-1] | IO1: Q2.11. What was the primary delivery mode for the course(s) in 2023? - [QID62%231-ChoiceTextEntryValue-3-1] | IP1: Q2.11. What was the primary delivery mode for the course(s) in 2023? - [QID62%231-ChoiceTextEntryValue-4-1] | IQ1: Q2.11. What was the primary delivery mode for the course(s) in 2023? - [QID62%231-ChoiceTextEntryValue-5-1] | IR1: Q2.11. What was the primary delivery mode for the course(s) in 2023? - [QID62%231-ChoiceTextEntryValue-6-1] | IS1: Q2.11. What was the primary delivery mode for the course(s) in 2023? - [QID62%231-ChoiceTextEntryValue-7-1] | IT1: Q2.11. What was the primary delivery mode for the course(s) in 2023? - [QID62%231-ChoiceTextEntryValue-8-1] | IU1: Q2.11. What was the primary delivery mode for the course(s) in 2023? - [QID62%231-ChoiceTextEntryValue-9-1] | IV1: Q2.11. What was the primary delivery mode for the course(s) in 2023? - [QID62%231-ChoiceTextEntryValue-10-1] | IW1: Q2.11. What was the primary delivery mode for the course(s) in 2023? - [QID62%231-ChoiceTextEntryValue-11-1] | IX1: Q2.11. What was the primary delivery mode for the course(s) in 2023? - [QID62%231-ChoiceTextEntryValue-12-1] | IY1: Q2.11. What was the primary delivery mode for the course(s) in 2023? - [QID62%231-ChoiceTextEntryValue-13-1] | IZ1: Q2.11. What was the primary delivery mode for the course(s) in 2023? - [QID62%231-ChoiceTextEntryValue-14-1] | JA1: Q2.11. What was the primary delivery mode for the course(s) in 2023? - [QID62%231-ChoiceTextEntryValue-15-1] | JB1: Q2.11. What was the primary delivery mode for the course(s) in 2023? - [QID62%231-ChoiceTextEntryValue-16-1] | JC1: Q2.11. What was the primary delivery mode for the course(s) in 2023? - [QID62%231-ChoiceTextEntryValue-17-1] | JD1: Q2.11. What was the primary delivery mode for the course(s) in 2023? - [QID62%231-ChoiceTextEntryValue-18-1] | JE1: Q2.11. What was the primary delivery mode for the course(s) in 2023? - [QID62%231-ChoiceTextEntryValue-19-1] | JF1: Q2.11. What was the primary delivery mode for the course(s) in 2023? - [QID62%231-ChoiceTextEntryValue-20-1] | JG1: Articulation Agreements Articulation agreements are formal agreements between education institutions that provide students with pathways and education access from secondary schools to two-year colleges and four-year colleges and universities. In 2023, did your ATE project create new articulation agreements or maintain articulation agreements that were previously created through your project? | JH1: Q2.12. Report the number of articulation agreements, institutions, and students associated with each education level. - Total number of articulation agreements developed in 2023 - High school to 2-year college | JI1: Q2.12. Report the number of articulation agreements, institutions, and students associated with each education level. - Total number of articulation agreements developed in 2023 - 2-year college to 4-year college | JJ1: Q2.12. Report the number of articulation agreements, institutions, and students associated with each education level. - Total number of articulation agreements in place in 2023 (sequential and co... - Total number of articulation agreements in place in 2023 (sequential and concurrent) - High school to 2-year college | JK1: Q2.12. Report the number of articulation agreements, institutions, and students associated with each education level. - Total number of articulation agreements in place in 2023 (sequential and co... - Total number of articulation agreements in place in 2023 (sequential and concurrent) - 2-year college to 4-year college | JL1: Q2.12. Report the number of articulation agreements, institutions, and students associated with each education level. - Number of institutions involved in all the agreements - High school to 2-year college | JM1: Q2.12. Report the number of articulation agreements, institutions, and students associated with each education level. - Number of institutions involved in all the agreements - 2-year college to 4-year college | JN1: Q2.12. Report the number of articulation agreements, institutions, and students associated with each education level. - Number of students who transferred in 2023 (enrolled at the higher educatio... - Number of students who transferred in 2023 (enrolled at the higher education level under the terms of an articulation agreement) - High school to 2-year college | JO1: Q2.12. Report the number of articulation agreements, institutions, and students associated with each education level. - Number of students who transferred in 2023 (enrolled at the higher educatio... - Number of students who transferred in 2023 (enrolled at the higher education level under the terms of an articulation agreement) - 2-year college to 4-year college | JP1: Educational Materials Development and Dissemination Educational materials include print or digital media designed for instructional or assessment purposes, such as - but not limited to - course and program curricula, tests, lab experiments, instructional modules, and textbooks for use in technician education. Do not use this section of the survey to report on: Materials created for promotion or marketing purposes. Instructional materials primarily used for faculty professional development. In 2023, did your ATE project create or substantially modify educational materials? | JQ1: In 2023, did your ATE project disseminate educational materials previously created (in 2022 or earlier) by your project? | JR1: Q2.13. How many of each of the following types of materials did you develop or modify in 2023? - Assessment activity or test - | JS1: Q2.13. How many of each of the following types of materials did you develop or modify in 2023? - Case study or problem set for problem-based learning - | JT1: Q2.13. How many of each of the following types of materials did you develop or modify in 2023? - Curriculum for a program - | JU1: Q2.13. How many of each of the following types of materials did you develop or modify in 2023? - Curriculum for a course - | JV1: Q2.13. How many of each of the following types of materials did you develop or modify in 2023? - Instructor guide/manual - | JW1: Q2.13. How many of each of the following types of materials did you develop or modify in 2023? - Interactive simulation - | JX1: Q2.13. How many of each of the following types of materials did you develop or modify in 2023? - Lab experiment - | JY1: Q2.13. How many of each of the following types of materials did you develop or modify in 2023? - Lesson plan - | JZ1: Q2.13. How many of each of the following types of materials did you develop or modify in 2023? - Module or instructional unit - | KA1: Q2.13. How many of each of the following types of materials did you develop or modify in 2023? - Textbook - | KB1: Q2.13. How many of each of the following types of materials did you develop or modify in 2023? - Videos - | KC1: Q2.13. How many of each of the following types of materials did you develop or modify in 2023? - Other (describe) - Text | KD1: Q2.13. How many of each of the following types of materials did you develop or modify in 2023? - Other (describe) - | KE1: Q2.14. Are you disseminating, or planning to disseminate, these materials in the following ways? - Commercial publication | KF1: Q2.14. Are you disseminating, or planning to disseminate, these materials in the following ways? - Project webpage or website | KG1: Q2.14. Are you disseminating, or planning to disseminate, these materials in the following ways? - Conference presentation or booth | KH1: Q2.14. Are you disseminating, or planning to disseminate, these materials in the following ways? - Workshop | KI1: Q2.14. Are you disseminating, or planning to disseminate, these materials in the following ways? - ATE Central | KJ1: Q2.14. Are you disseminating, or planning to disseminate, these materials in the following ways? - Clearinghouse or repository maintained by an external organization other than ATE Central (describe) | KK1: Q2.14. Are you disseminating, or planning to disseminate, these materials in the following ways? - Clearinghouse or repository maintained by an external organization other than ATE Central (describe) - Text | KL1: Q2.14. Are you disseminating, or planning to disseminate, these materials in the following ways? - Other (describe) | KM1: Q2.14. Are you disseminating, or planning to disseminate, these materials in the following ways? - Other (describe) - Text | KN1: Q2.15. Which of the following types of materials previously created (in 2022 or earlier) by your project did you disseminate in 2023? - Assessment activity or test | KO1: Q2.15. Which of the following types of materials previously created (in 2022 or earlier) by your project did you disseminate in 2023? - Case study or problem set for problem-based learning | KP1: Q2.15. Which of the following types of materials previously created (in 2022 or earlier) by your project did you disseminate in 2023? - Curriculum for a program | KQ1: Q2.15. Which of the following types of materials previously created (in 2022 or earlier) by your project did you disseminate in 2023? - Curriculum for a course | KR1: Q2.15. Which of the following types of materials previously created (in 2022 or earlier) by your project did you disseminate in 2023? - Instructor guide/manual | KS1: Q2.15. Which of the following types of materials previously created (in 2022 or earlier) by your project did you disseminate in 2023? - Interactive simulation | KT1: Q2.15. Which of the following types of materials previously created (in 2022 or earlier) by your project did you disseminate in 2023? - Lab experiment | KU1: Q2.15. Which of the following types of materials previously created (in 2022 or earlier) by your project did you disseminate in 2023? - Lesson plan | KV1: Q2.15. Which of the following types of materials previously created (in 2022 or earlier) by your project did you disseminate in 2023? - Module or instructional unit | KW1: Q2.15. Which of the following types of materials previously created (in 2022 or earlier) by your project did you disseminate in 2023? - Textbook | KX1: Q2.15. Which of the following types of materials previously created (in 2022 or earlier) by your project did you disseminate in 2023? - Videos | KY1: Q2.15. Which of the following types of materials previously created (in 2022 or earlier) by your project did you disseminate in 2023? - Other (describe) | KZ1: Q2.15. Which of the following types of materials previously created (in 2022 or earlier) by your project did you disseminate in 2023? - Other (describe) - Text | LA1: Q2.16. Did you disseminate these materials in the following ways? - Commercial publication | LB1: Q2.16. Did you disseminate these materials in the following ways? - Project webpage or website | LC1: Q2.16. Did you disseminate these materials in the following ways? - Conference presentation or booth | LD1: Q2.16. Did you disseminate these materials in the following ways? - Workshop | LE1: Q2.16. Did you disseminate these materials in the following ways? - ATE Central | LF1: Q2.16. Did you disseminate these materials in the following ways? - Clearinghouse or repository maintained by an external organization other than ATE Central (describe) | LG1: Q2.16. Did you disseminate these materials in the following ways? - Clearinghouse or repository maintained by an external organization other than ATE Central (describe) - Text | LH1: Q2.16. Did you disseminate these materials in the following ways? - Other (describe) | LI1: Q2.16. Did you disseminate these materials in the following ways? - Other (describe) - Text | LJ1: Q2.17. Does your ATE project track the number of other institutions that are using the program and/or course curriculum created by your project? | LK1: Q2.17.1. How many other institutions are using the program and/or course curriculum created by your project? | LL1: Acquisition of Instruments and Equipment Instruments are equipment are physical items used in instruction in technical courses to help students learn processes, understand concepts, or how to perform tasks. Some examples may include: Laboratory or field instrumentation Scientific or industrial machinery Computer related hardware or software Do not use this section of the survey to report on: Instruments and equipment that were donated to your project. Instruments and equipment that were purchased with non-ATE funding. In 2023, did your ATE project purchase instrumentation and equipment for use in instruction with ATE funding? | LM1: Q2.18. How much did your project spend on instrumentation and equipment in 2023? (Use a numeric response. Do not use a symbol, such as a dollar sign "$") | LN1: Q2.19. Which of the following best describes how your project uses this instrumentation and equipment? - Selected Choice | LO1: Q2.19. Which of the following best describes how your project uses this instrumentation and equipment? - Other (describe) - Text | LP1: Q2.20. How many courses, students, and educators used this instrumentation and equipment in 2023? - Courses | LQ1: Q2.20. How many courses, students, and educators used this instrumentation and equipment in 2023? - Students | LR1: Q2.20. How many courses, students, and educators used this instrumentation and equipment in 2023? - Educators | LS1: Q2.21. How did acquiring this instrumentation or equipment enhance student learning? | LT1: Business and Entrepreneurial Skills Development Business and entrepreneurial skills development are systematic efforts that help students to develop their skills in areas such as - but not limited to - business development, marketing, networking, and understanding the global marketplace. Do not use this section of the survey to report on: Activities with a primary focus other than business or entrepreneurial skills development (such as courses or workshops on other topics that might also have an indirect effect on these skills). Activities that did not involve working with students directly. In 2023, did your ATE project work with students specifically to develop their business and entrepreneurial skills? | LU1: Q3.1. Did your project work with students to develop their business and entrepreneurial skills in the following ways? - Activity/course unit | LV1: Q3.1. Did your project work with students to develop their business and entrepreneurial skills in the following ways? - Club | LW1: Q3.1. Did your project work with students to develop their business and entrepreneurial skills in the following ways? - Entire course | LX1: Q3.1. Did your project work with students to develop their business and entrepreneurial skills in the following ways? - Incubator program | LY1: Q3.1. Did your project work with students to develop their business and entrepreneurial skills in the following ways? - Mentoring or coaching | LZ1: Q3.1. Did your project work with students to develop their business and entrepreneurial skills in the following ways? - Online lesson or material | MA1: Q3.1. Did your project work with students to develop their business and entrepreneurial skills in the following ways? - Workshop | MB1: Q3.1. Did your project work with students to develop their business and entrepreneurial skills in the following ways? - Other | MC1: Q3.1. Did your project work with students to develop their business and entrepreneurial skills in the following ways? - Other - Text | MD1: Q3.2. How many students participated in business and entrepreneurial skills development provided by your project in 2023? | ME1: Workplace-Based Learning Workplace-based learning includes any situation in which a student gains experience at a work site, such as internships, apprenticeships, job shadowing, and field trips to industry sites. Do not use this section of the survey to report on: Activities that took place in a school setting. In 2023, did your ATE project offer workplace-based learning to students? | MF1: Q3.3. Did your ATE project offer the following workplace-based learning opportunities in 2023? - Field trips to business/industry sites | MG1: Q3.3. Did your ATE project offer the following workplace-based learning opportunities in 2023? - Job shadowing | MH1: Q3.3. Did your ATE project offer the following workplace-based learning opportunities in 2023? - Apprenticeships | MI1: Q3.3. Did your ATE project offer the following workplace-based learning opportunities in 2023? - Externships | MJ1: Q3.3. Did your ATE project offer the following workplace-based learning opportunities in 2023? - Internships | MK1: Q3.3. Did your ATE project offer the following workplace-based learning opportunities in 2023? - Co-op learning | ML1: Q3.3. Did your ATE project offer the following workplace-based learning opportunities in 2023? - Other (describe) | MM1: Q3.3. Did your ATE project offer the following workplace-based learning opportunities in 2023? - Other (describe) - Text | MN1: Q3.3.1. Were any of your apprenticeships offered in 2023 registered with the U.S. Department of Labor or a state apprenticeship agency (i.e., a "registered apprenticeship")? | MO1: Q3.4. About how much time did a student typically commit to each type of workplace-based learning... - How many hours per week did a student commit to this activity? - Job shadowing - | MP1: Q3.4. About how much time did a student typically commit to each type of workplace-based learning... - How many hours per week did a student commit to this activity? - Apprenticeships - | MQ1: Q3.4. About how much time did a student typically commit to each type of workplace-based learning... - How many hours per week did a student commit to this activity? - Externships - | MR1: Q3.4. About how much time did a student typically commit to each type of workplace-based learning... - How many hours per week did a student commit to this activity? - Internships - | MS1: Q3.4. About how much time did a student typically commit to each type of workplace-based learning... - How many hours per week did a student commit to this activity? - Co-op learning - | MT1: Q3.4. About how much time did a student typically commit to each type of workplace-based learning... - How many hours per week did a student commit to this activity? - Other [QID76-ChoiceTextEntryValue-7] - | MU1: Q3.4. About how much time did a student typically commit to each type of workplace-based learning... - How many weeks per year did a student commit to this activity? - Job shadowing - | MV1: Q3.4. About how much time did a student typically commit to each type of workplace-based learning... - How many weeks per year did a student commit to this activity? - Apprenticeships - | MW1: Q3.4. About how much time did a student typically commit to each type of workplace-based learning... - How many weeks per year did a student commit to this activity? - Externships - | MX1: Q3.4. About how much time did a student typically commit to each type of workplace-based learning... - How many weeks per year did a student commit to this activity? - Internships - | MY1: Q3.4. About how much time did a student typically commit to each type of workplace-based learning... - How many weeks per year did a student commit to this activity? - Co-op learning - | MZ1: Q3.4. About how much time did a student typically commit to each type of workplace-based learning... - How many weeks per year did a student commit to this activity? - Other [QID76-ChoiceTextEntryValue-7] - | NA1: Q3.5. Which of these characteristics apply to the workplace-based learning opportunities offered... - Students received payment - Job shadowing | NB1: Q3.5. Which of these characteristics apply to the workplace-based learning opportunities offered... - Students received payment - Apprenticeships | NC1: Q3.5. Which of these characteristics apply to the workplace-based learning opportunities offered... - Students received payment - Externships | ND1: Q3.5. Which of these characteristics apply to the workplace-based learning opportunities offered... - Students received payment - Internships | NE1: Q3.5. Which of these characteristics apply to the workplace-based learning opportunities offered... - Students received payment - Co-op learning | NF1: Q3.5. Which of these characteristics apply to the workplace-based learning opportunities offered... - Students received payment - Other [QID76-ChoiceTextEntryValue-7] | NG1: Q3.5. Which of these characteristics apply to the workplace-based learning opportunities offered... - Students received academic credit - Job shadowing | NH1: Q3.5. Which of these characteristics apply to the workplace-based learning opportunities offered... - Students received academic credit - Apprenticeships | NI1: Q3.5. Which of these characteristics apply to the workplace-based learning opportunities offered... - Students received academic credit - Externships | NJ1: Q3.5. Which of these characteristics apply to the workplace-based learning opportunities offered... - Students received academic credit - Internships | NK1: Q3.5. Which of these characteristics apply to the workplace-based learning opportunities offered... - Students received academic credit - Co-op learning | NL1: Q3.5. Which of these characteristics apply to the workplace-based learning opportunities offered... - Students received academic credit - Other [QID76-ChoiceTextEntryValue-7] | NM1: Q3.5. Which of these characteristics apply to the workplace-based learning opportunities offered... - Coupled with specific course(s) - Job shadowing | NN1: Q3.5. Which of these characteristics apply to the workplace-based learning opportunities offered... - Coupled with specific course(s) - Apprenticeships | NO1: Q3.5. Which of these characteristics apply to the workplace-based learning opportunities offered... - Coupled with specific course(s) - Externships | NP1: Q3.5. Which of these characteristics apply to the workplace-based learning opportunities offered... - Coupled with specific course(s) - Internships | NQ1: Q3.5. Which of these characteristics apply to the workplace-based learning opportunities offered... - Coupled with specific course(s) - Co-op learning | NR1: Q3.5. Which of these characteristics apply to the workplace-based learning opportunities offered... - Coupled with specific course(s) - Other [QID76-ChoiceTextEntryValue-7] | NS1: Q3.5. Which of these characteristics apply to the workplace-based learning opportunities offered... - Student participation required by program - Job shadowing | NT1: Q3.5. Which of these characteristics apply to the workplace-based learning opportunities offered... - Student participation required by program - Apprenticeships | NU1: Q3.5. Which of these characteristics apply to the workplace-based learning opportunities offered... - Student participation required by program - Externships | NV1: Q3.5. Which of these characteristics apply to the workplace-based learning opportunities offered... - Student participation required by program - Internships | NW1: Q3.5. Which of these characteristics apply to the workplace-based learning opportunities offered... - Student participation required by program - Co-op learning | NX1: Q3.5. Which of these characteristics apply to the workplace-based learning opportunities offered... - Student participation required by program - Other [QID76-ChoiceTextEntryValue-7] | NY1: Q3.6. How many students participated in each type of workplace-based learning provided by your project in 2023? - Field trips to business/industry sites - Number of students | NZ1: Q3.6. How many students participated in each type of workplace-based learning provided by your project in 2023? - Job shadowing - Number of students | OA1: Q3.6. How many students participated in each type of workplace-based learning provided by your project in 2023? - Apprenticeships - Number of students | OB1: Q3.6. How many students participated in each type of workplace-based learning provided by your project in 2023? - Externships - Number of students | OC1: Q3.6. How many students participated in each type of workplace-based learning provided by your project in 2023? - Internships - Number of students | OD1: Q3.6. How many students participated in each type of workplace-based learning provided by your project in 2023? - Co-op Learning - Number of students | OE1: Q3.6. How many students participated in each type of workplace-based learning provided by your project in 2023? - Other [QID76-ChoiceTextEntryValue-7] - Number of students | OF1: Q3.7. What are the most valuable aspects of workplace-based learning for your students? | OG1: Student Mentoring Student mentoring involves an experienced industry professional, educator, or advanced student providing guidance and advice to help a less experienced student develop the skills and knowledge they need to enhance their academic and professional growth. Do not use use this section of the survey to report on: Mentoring or coaching intended for educators or other professionals. Mentoring provided to students on an informal or ad hoc basis. In 2023, did your ATE project offer formal mentoring or coaching opportunities to students? | OH1: Q3.8. Did the following types of individuals provide mentoring or coaching through your ATE project (i.e., served as the mentors)? - Business and industry professionals | OI1: Q3.8. Did the following types of individuals provide mentoring or coaching through your ATE project (i.e., served as the mentors)? - Educational faculty or staff | OJ1: Q3.8. Did the following types of individuals provide mentoring or coaching through your ATE project (i.e., served as the mentors)? - Students/peers | OK1: Q3.8. Did the following types of individuals provide mentoring or coaching through your ATE project (i.e., served as the mentors)? - Other (describe) | OL1: Q3.8. Did the following types of individuals provide mentoring or coaching through your ATE project (i.e., served as the mentors)? - Other (describe) - Text | OM1: Q3.9. Are the mentors trained in mentoring by your project? | ON1: Q3.10. How many students received mentoring or coaching through your ATE project in 2023? - High school students - Number of Students | OO1: Q3.10. How many students received mentoring or coaching through your ATE project in 2023? - 2-year college students - Number of Students | OP1: Q3.10. How many students received mentoring or coaching through your ATE project in 2023? - 4-year college students - Number of Students | OQ1: Q3.10. How many students received mentoring or coaching through your ATE project in 2023? - Other (describe) - Text | OR1: Q3.10. How many students received mentoring or coaching through your ATE project in 2023? - Other (describe) - Number of Students | OS1: Student Competitions Student competitions are events at which students compete as individuals or teams using skills related to a STEM discipline or industry. Do not use this section to report on: Student involvement in competitions not hosted or organized by your project. In 2023, did your ATE project host or organize a student competition? | OT1: Q3.11. How many competitions were hosted or organized by your ATE project in 2023? | OU1: Q3.12. How many students participated in the competitions hosted or organized by your ATE project in 2023? | OV1: Programs to Support Transition into College Programs to support transition into college are systematic efforts to equip students with the skills they need to successfully navigate college. Examples include - but are not limited to - summer bridge programs, college readiness workshops or classes, first-year programs, support for non-traditional students, or other activities. Do not use this section of the survey to report on: Support provided to transitioning students on an ad hoc or informal basis. Indirect support (such as guidance for faculty or staff on how to support transitioning students). In 2023, did your project offer formal programs to help students transition into college? | OW1: Q3.13. How many transition programs were supported by your ATE project in 2023? | OX1: Q3.14. List the transition programs supported by your ATE project in 2023. - What is the name of the program? - Program 1 - | OY1: Q3.14. List the transition programs supported by your ATE project in 2023. - What is the name of the program? - Program 2 - | OZ1: Q3.14. List the transition programs supported by your ATE project in 2023. - What is the name of the program? - Program 3 - | PA1: Q3.14. List the transition programs supported by your ATE project in 2023. - What is the name of the program? - Program 4 - | PB1: Q3.14. List the transition programs supported by your ATE project in 2023. - What is the name of the program? - Program 5 - | PC1: Q3.14. List the transition programs supported by your ATE project in 2023. - Who is the primary audience? - Program 1 | PD1: Q3.14. List the transition programs supported by your ATE project in 2023. - Who is the primary audience? - Program 2 | PE1: Q3.14. List the transition programs supported by your ATE project in 2023. - Who is the primary audience? - Program 3 | PF1: Q3.14. List the transition programs supported by your ATE project in 2023. - Who is the primary audience? - Program 4 | PG1: Q3.14. List the transition programs supported by your ATE project in 2023. - Who is the primary audience? - Program 5 | PH1: Q3.14. List the transition programs supported by your ATE project in 2023. - How many students participated? - Program 1 - | PI1: Q3.14. List the transition programs supported by your ATE project in 2023. - How many students participated? - Program 2 - | PJ1: Q3.14. List the transition programs supported by your ATE project in 2023. - How many students participated? - Program 3 - | PK1: Q3.14. List the transition programs supported by your ATE project in 2023. - How many students participated? - Program 4 - | PL1: Q3.14. List the transition programs supported by your ATE project in 2023. - How many students participated? - Program 5 - | PM1: Activities to Help Students Obtain Industry-Recognized Certifications or Licensing Industry-recognized certifications or licenses serve as evidence that a person has specific skills or knowledge. Certifications are typically awarded by non-governmental agencies; licenses are regulated by the government. Do not use this section to report on: Academic certificates or badges awarded by a college. General academic preparation to work in industry. In 2023, did your ATE project work with students to support them in obtaining specific industry-recognized certifications or licenses? | PN1: Are there industry-validated certifications relevant to the jobs your project prepares students for? | PO1: Q3.15. Did your ATE project support students in obtaining these certifications or licenses in the following ways? - Provide financial assistance for testing fees | PP1: Q3.15. Did your ATE project support students in obtaining these certifications or licenses in the following ways? - Serve as a testing center | PQ1: Q3.15. Did your ATE project support students in obtaining these certifications or licenses in the following ways? - Provide specific test preparation workshops or learning modules | PR1: Q3.15. Did your ATE project support students in obtaining these certifications or licenses in the following ways? - Review students' certification or license applications | PS1: Q3.15. Did your ATE project support students in obtaining these certifications or licenses in the following ways? - Existing courses aligned with license or certification requirements | PT1: Q3.15. Did your ATE project support students in obtaining these certifications or licenses in the following ways? - Other (describe) | PU1: Q3.15. Did your ATE project support students in obtaining these certifications or licenses in the following ways? - Other (describe) - Text | PV1: Q3.16. Did the following types of organization(s) award the licenses or certifications that your project helps students obtain? - Government agency | PW1: Q3.16. Did the following types of organization(s) award the licenses or certifications that your project helps students obtain? - Non-governmental organization (e.g., professional society, industry group) | PX1: Q3.16. Did the following types of organization(s) award the licenses or certifications that your project helps students obtain? - For-profit corporation or company | PY1: Q3.16. Did the following types of organization(s) award the licenses or certifications that your project helps students obtain? - Other (describe) | PZ1: Q3.16. Did the following types of organization(s) award the licenses or certifications that your project helps students obtain? - Other (describe) - Text | QA1: Q3.17. What are the name(s) of the certification(s) relevant to jobs your project prepares students for? | QB1: Q3.18. Do you include information in your program or courses to support students gaining relevant certification(s)? | QC1: Q3.19. Does your regional industry list the certification(s) in job announcements? | QD1: Q3.19.a. Please name the industry and the certification(s) they list. | QE1: Professional Development for Educators or Future Educators Professional development for educators involves systematic efforts to work with secondary school teachers, college faculty, or preservice teachers to enhance their disciplinary capabilities, teaching skills, or understanding of current technologies and practices in ways that will directly impact technician education. Do not use this section of the survey to report on: Professional development or training for ATE program grantseekers or current grantees (that is addressed in Section 8: ATE Program Services and Support). Activities that are not intentionally geared towards educators or future educators.Conference presentations or other outreach activities (e.g., webinars, information sessions, video, keynote). In 2023, did your ATE project provide training or professional development to current or future educators? | QF1: Q4.1. How many professional development activities of each length listed below were offered by your project in 2023? - Instructional activities of one day or less (e.g., one-day workshop) - Total Number of Activities Offered | QG1: Q4.1. How many professional development activities of each length listed below were offered by your project in 2023? - Instructional activities that lasted more than one day but less than one we... - Instructional activities that lasted more than one day but less than one week (e.g., workshop, online module) - Total Number of Activities Offered | QH1: Q4.1. How many professional development activities of each length listed below were offered by your project in 2023? - Instructional activities that lasted from one to several weeks (e.g., cours... - Instructional activities that lasted from one to several weeks (e.g., course, summer institute) - Total Number of Activities Offered | QI1: Q4.1. How many professional development activities of each length listed below were offered by your project in 2023? - Long-term periodic instructional activities (e.g., internship, peer coachin... - Long-term periodic instructional activities (e.g., internship, peer coaching) - Total Number of Activities Offered | QK1: Q4.2. How many individuals were served by these professional development activities in 2023? - Instructional activities of one day or less (e.g., one-day workshop) - Preservice Teachers | QL1: Q4.2. How many individuals were served by these professional development activities in 2023? - Instructional activities of one day or less (e.g., one-day workshop) - High School Teachers | QM1: Q4.2. How many individuals were served by these professional development activities in 2023? - Instructional activities of one day or less (e.g., one-day workshop) - 2-Year College Faculty | QN1: Q4.2. How many individuals were served by these professional development activities in 2023? - Instructional activities of one day or less (e.g., one-day workshop) - 4-Year College Faculty | QO1: Q4.2. How many individuals were served by these professional development activities in 2023? - Instructional activities of one day or less (e.g., one-day workshop) - Other or Unknown | QP1: Q4.2. How many individuals were served by these professional development activities in 2023? - Instructional activities that lasted more than one day but less than one we... - Instructional activities that lasted more than one day but less than one week (e.g., workshop, online module) - Preservice Teachers | QQ1: Q4.2. How many individuals were served by these professional development activities in 2023? - Instructional activities that lasted more than one day but less than one we... - Instructional activities that lasted more than one day but less than one week (e.g., workshop, online module) - High School Teachers | QR1: Q4.2. How many individuals were served by these professional development activities in 2023? - Instructional activities that lasted more than one day but less than one we... - Instructional activities that lasted more than one day but less than one week (e.g., workshop, online module) - 2-Year College Faculty | QS1: Q4.2. How many individuals were served by these professional development activities in 2023? - Instructional activities that lasted more than one day but less than one we... - Instructional activities that lasted more than one day but less than one week (e.g., workshop, online module) - 4-Year College Faculty | QT1: Q4.2. How many individuals were served by these professional development activities in 2023? - Instructional activities that lasted more than one day but less than one we... - Instructional activities that lasted more than one day but less than one week (e.g., workshop, online module) - Other or Unknown | QU1: Q4.2. How many individuals were served by these professional development activities in 2023? - Instructional activities that lasted from one to several weeks (e.g., cours... - Instructional activities that lasted from one to several weeks (e.g., course, summer institute) - Preservice Teachers | QV1: Q4.2. How many individuals were served by these professional development activities in 2023? - Instructional activities that lasted from one to several weeks (e.g., cours... - Instructional activities that lasted from one to several weeks (e.g., course, summer institute) - High School Teachers | QW1: Q4.2. How many individuals were served by these professional development activities in 2023? - Instructional activities that lasted from one to several weeks (e.g., cours... - Instructional activities that lasted from one to several weeks (e.g., course, summer institute) - 2-Year College Faculty | QX1: Q4.2. How many individuals were served by these professional development activities in 2023? - Instructional activities that lasted from one to several weeks (e.g., cours... - Instructional activities that lasted from one to several weeks (e.g., course, summer institute) - 4-Year College Faculty | QY1: Q4.2. How many individuals were served by these professional development activities in 2023? - Instructional activities that lasted from one to several weeks (e.g., cours... - Instructional activities that lasted from one to several weeks (e.g., course, summer institute) - Other or Unknown | QZ1: Q4.2. How many individuals were served by these professional development activities in 2023? - Long-term periodic instructional activities (e.g., internship, peer coachin... - Long-term periodic instructional activities (e.g., internship, peer coaching) - Preservice Teachers | RA1: Q4.2. How many individuals were served by these professional development activities in 2023? - Long-term periodic instructional activities (e.g., internship, peer coachin... - Long-term periodic instructional activities (e.g., internship, peer coaching) - High School Teachers | RB1: Q4.2. How many individuals were served by these professional development activities in 2023? - Long-term periodic instructional activities (e.g., internship, peer coachin... - Long-term periodic instructional activities (e.g., internship, peer coaching) - 2-Year College Faculty | RC1: Q4.2. How many individuals were served by these professional development activities in 2023? - Long-term periodic instructional activities (e.g., internship, peer coachin... - Long-term periodic instructional activities (e.g., internship, peer coaching) - 4-Year College Faculty | RD1: Q4.2. How many individuals were served by these professional development activities in 2023? - Long-term periodic instructional activities (e.g., internship, peer coachin... - Long-term periodic instructional activities (e.g., internship, peer coaching) - Other or Unknown | RE1: Q4.3. Are the following topics covered by your professional development? - Pedagogy | RF1: Q4.3. Are the following topics covered by your professional development? - Discipline- or industry-specific knowledge or skills | RG1: Q4.3. Are the following topics covered by your professional development? - Recruitment or retention of students | RH1: Q4.3. Are the following topics covered by your professional development? - Training on specific equipment | RI1: Q4.3. Are the following topics covered by your professional development? - Addressing issues of equity, diversity, or inclusion | RJ1: Q4.3. Are the following topics covered by your professional development? - Employability skills (i.e., leadership, communication, teamwork, critical and creative thinking, human behavior) | RK1: Q4.3. Are the following topics covered by your professional development? - Other (describe) | RL1: Q4.3. Are the following topics covered by your professional development? - Other (describe) - Text | RM1: Q4.4. Does your project collect data about the number of students taught by the educators who participated in professional development provided by your project? | RN1: Q4.4.1. How many students were taught by the educators who participated in the professional development offered by your ATE project in 2023? | RO1: Conferences or Meetings ATE-related conferences or meetings are events held for the purpose of professional exchange about issues related to advanced technological education. Do not use this section of the survey to report on: Attendance or presentations at conferences (e.g., presenting at HI-TEC or ATE PI Conference). Events held primarily for training purposes. Typical management or advisory meetings that most projects hold as part of their normal operations (e.g., advisory committee meetings, partner meetings, BILT meetings). In 2023, did your ATE project organize a conference or meeting? | RP1: Q5.1. Was hosting a conference the main purpose of your project (i.e., project was funded with a "conference" grant)? | RQ1: Conferences Recode | RR1: Q5.2. How many conferences, meetings, or other events did your project organize in 2023? | RS1: Q5.3. What was the name of each conference, meeting, or other event your project organized in 2023? - Event 1 | RT1: Q5.3. What was the name of each conference, meeting, or other event your project organized in 2023? - Event 2 | RU1: Q5.3. What was the name of each conference, meeting, or other event your project organized in 2023? - Event 3 | RV1: Q5.3. What was the name of each conference, meeting, or other event your project organized in 2023? - Event 4 | RW1: Q5.3. What was the name of each conference, meeting, or other event your project organized in 2023? - Event 5 | RX1: Q5.4. How many people attended each event? - [QID102-ChoiceTextEntryValue-1] | RY1: Q5.4. How many people attended each event? - [QID102-ChoiceTextEntryValue-2] | RZ1: Q5.4. How many people attended each event? - [QID102-ChoiceTextEntryValue-3] | SA1: Q5.4. How many people attended each event? - [QID102-ChoiceTextEntryValue-4] | SB1: Q5.4. How many people attended each event? - [QID102-ChoiceTextEntryValue-5] | SC1: Applied Research Applied or targeted research is research intended to build the knowledge base about the education and development of the skilled technical workforce in STEM fields. Do not use this section of the survey to report on: Your project's evaluation, which may utilize research methods. General background research to inform your project's implementation. In 2023, did your ATE project conduct applied research? | SD1: Q6.1. How many research studies has your project conducted in 2023? (If you have more than 7 studies, please contact Erika Sturgis at atesurvey@evalu-ate.org) | SE1: Q6.2. What is/are the name(s) of the research study(ies) conducted in 2023? - Study 1 | SF1: Q6.2. What is/are the name(s) of the research study(ies) conducted in 2023? - Study 2 | SG1: Q6.2. What is/are the name(s) of the research study(ies) conducted in 2023? - Study 3 | SH1: Q6.2. What is/are the name(s) of the research study(ies) conducted in 2023? - Study 4 | SI1: Q6.2. What is/are the name(s) of the research study(ies) conducted in 2023? - Study 5 | SJ1: Q6.2. What is/are the name(s) of the research study(ies) conducted in 2023? - Study 6 | SK1: Q6.2. What is/are the name(s) of the research study(ies) conducted in 2023? - Study 7 | SL1: Q6.3. Which of the following best describes the current stage of your study entitled [QID1318447236-ChoiceTextEntryValue-3]? | SM1: Q6.4. Briefly describe your primary research questions of your study entitled [QID1318447236-ChoiceTextEntryValue-3] (i.e., overarching questions that guide your research study, not specific data collection questions). | SN1: Q6.5. Who is the target population of your research study [QID1318447236-ChoiceTextEntryValue-3] (i.e., what population does your sample represent)? | SO1: Q6.6. Which of the following research designs are being used in your research study [QID1318447236-ChoiceTextEntryValue-3]? (Please select all that apply.) - Selected Choice - Descriptive (e.g., case study, naturalistic observation, survey) | SP1: Q6.6. Which of the following research designs are being used in your research study [QID1318447236-ChoiceTextEntryValue-3]? (Please select all that apply.) - Selected Choice - Correlational (e.g., case-control study, longitudinal analysis) | SQ1: Q6.6. Which of the following research designs are being used in your research study [QID1318447236-ChoiceTextEntryValue-3]? (Please select all that apply.) - Selected Choice - Experimental or quasi-experimental | SR1: Q6.6. Which of the following research designs are being used in your research study [QID1318447236-ChoiceTextEntryValue-3]? (Please select all that apply.) - Selected Choice - Review (e.g., literature review or systematic review) | SS1: Q6.6. Which of the following research designs are being used in your research study [QID1318447236-ChoiceTextEntryValue-3]? (Please select all that apply.) - Selected Choice - Meta-analytic | ST1: Q6.6. Which of the following research designs are being used in your research study [QID1318447236-ChoiceTextEntryValue-3]? (Please select all that apply.) - Selected Choice - Other (describe) | SU1: Q6.6. Which of the following research designs are being used in your research study [QID1318447236-ChoiceTextEntryValue-3]? (Please select all that apply.) - Other (describe) - Text | SV1: Q6.7. Briefly summarize the main results from your research study [QID1318447236-ChoiceTextEntryValue-3]. | SW1: Q6.8. Are you disseminating or planning on disseminating the results of your research study [QID1318447236-ChoiceTextEntryValue-3] in the following ways? - Article in an academic journal | SX1: Q6.8. Are you disseminating or planning on disseminating the results of your research study [QID1318447236-ChoiceTextEntryValue-3] in the following ways? - Article in practitioner journal | SY1: Q6.8. Are you disseminating or planning on disseminating the results of your research study [QID1318447236-ChoiceTextEntryValue-3] in the following ways? - Article in a magazine | SZ1: Q6.8. Are you disseminating or planning on disseminating the results of your research study [QID1318447236-ChoiceTextEntryValue-3] in the following ways? - Report available for free online (e.g., white paper or working paper) | TA1: Q6.8. Are you disseminating or planning on disseminating the results of your research study [QID1318447236-ChoiceTextEntryValue-3] in the following ways? - Conference presentation | TB1: Q6.8. Are you disseminating or planning on disseminating the results of your research study [QID1318447236-ChoiceTextEntryValue-3] in the following ways? - Blog or newsletter | TC1: Q6.8. Are you disseminating or planning on disseminating the results of your research study [QID1318447236-ChoiceTextEntryValue-3] in the following ways? - Other (describe) | TD1: Q6.8. Are you disseminating or planning on disseminating the results of your research study [QID1318447236-ChoiceTextEntryValue-3] in the following ways? - Other (describe) - Text | TE1: Q6.9. If any of your research results are published online for [QID1318447236-ChoiceTextEntryValue-3], please provide a URL: | TF1: Q6.3. Which of the following best describes the current stage of your study entitled [QID1318447236-ChoiceTextEntryValue-4]? | TG1: Q6.4. Briefly describe your primary research questions of your study entitled [QID1318447236-ChoiceTextEntryValue-4] (i.e., overarching questions that guide your research study, not specific data collection questions). | TH1: Q6.5. Who is the target population of your research study [QID1318447236-ChoiceTextEntryValue-4] (i.e., what population does your sample represent)? | TI1: Q6.6. Which of the following research designs are being used in your research study [QID1318447236-ChoiceTextEntryValue-4]? - Selected Choice - Descriptive (e.g., case study, naturalistic observation, survey) | TJ1: Q6.6. Which of the following research designs are being used in your research study [QID1318447236-ChoiceTextEntryValue-4]? - Selected Choice - Correlational (e.g., case-control study, longitudinal analysis) | TK1: Q6.6. Which of the following research designs are being used in your research study [QID1318447236-ChoiceTextEntryValue-4]? - Selected Choice - Experimental or quasi-experimental | TL1: Q6.6. Which of the following research designs are being used in your research study [QID1318447236-ChoiceTextEntryValue-4]? - Selected Choice - Review (e.g., literature review or systematic review) | TM1: Q6.6. Which of the following research designs are being used in your research study [QID1318447236-ChoiceTextEntryValue-4]? - Selected Choice - Meta-analytic | TN1: Q6.6. Which of the following research designs are being used in your research study [QID1318447236-ChoiceTextEntryValue-4]? - Selected Choice - Other (describe) | TO1: Q6.6. Which of the following research designs are being used in your research study [QID1318447236-ChoiceTextEntryValue-4]? - Other (describe) - Text | TP1: Q6.7. Briefly summarize the main results from your research study [QID1318447236-ChoiceTextEntryValue-4]. | TQ1: Q6.8. Are you disseminating or planning on disseminating the results of your research study [QID1318447236-ChoiceTextEntryValue-4] in the following ways? - Article in an academic journal | TR1: Q6.8. Are you disseminating or planning on disseminating the results of your research study [QID1318447236-ChoiceTextEntryValue-4] in the following ways? - Article in practitioner journal | TS1: Q6.8. Are you disseminating or planning on disseminating the results of your research study [QID1318447236-ChoiceTextEntryValue-4] in the following ways? - Article in a magazine | TT1: Q6.8. Are you disseminating or planning on disseminating the results of your research study [QID1318447236-ChoiceTextEntryValue-4] in the following ways? - Report available for free online (e.g., white paper or working paper) | TU1: Q6.8. Are you disseminating or planning on disseminating the results of your research study [QID1318447236-ChoiceTextEntryValue-4] in the following ways? - Conference presentation | TV1: Q6.8. Are you disseminating or planning on disseminating the results of your research study [QID1318447236-ChoiceTextEntryValue-4] in the following ways? - Blog or newsletter | TW1: Q6.8. Are you disseminating or planning on disseminating the results of your research study [QID1318447236-ChoiceTextEntryValue-4] in the following ways? - Other (describe) | TX1: Q6.8. Are you disseminating or planning on disseminating the results of your research study [QID1318447236-ChoiceTextEntryValue-4] in the following ways? - Other (describe) - Text | TY1: Q6.9. If any of your research results are published online for [QID1318447236-ChoiceTextEntryValue-4], please provide a URL: | TZ1: Q6.3. Which of the following best describes the current stage of your study entitled [QID1318447236-ChoiceTextEntryValue-5]? | UA1: Q6.4. Briefly describe your primary research questions of your study entitled [QID1318447236-ChoiceTextEntryValue-5] (i.e., overarching questions that guide your research study, not specific data collection questions). | UB1: Q6.5. Who is the target population of your research study [QID1318447236-ChoiceTextEntryValue-5] (i.e., what population does your sample represent)? | UC1: Q6.6. Which of the following research designs are being used in your research study [QID1318447236-ChoiceTextEntryValue-5]? - Selected Choice - Descriptive (e.g., case study, naturalistic observation, survey) | UD1: Q6.6. Which of the following research designs are being used in your research study [QID1318447236-ChoiceTextEntryValue-5]? - Selected Choice - Correlational (e.g., case-control study, longitudinal analysis) | UE1: Q6.6. Which of the following research designs are being used in your research study [QID1318447236-ChoiceTextEntryValue-5]? - Selected Choice - Experimental or quasi-experimental | UF1: Q6.6. Which of the following research designs are being used in your research study [QID1318447236-ChoiceTextEntryValue-5]? - Selected Choice - Review (e.g., literature review or systematic review) | UG1: Q6.6. Which of the following research designs are being used in your research study [QID1318447236-ChoiceTextEntryValue-5]? - Selected Choice - Meta-analytic | UH1: Q6.6. Which of the following research designs are being used in your research study [QID1318447236-ChoiceTextEntryValue-5]? - Selected Choice - Other (describe) | UI1: Q6.6. Which of the following research designs are being used in your research study [QID1318447236-ChoiceTextEntryValue-5]? - Other (describe) - Text | UJ1: Q6.7. Briefly summarize the main results from your research study [QID1318447236-ChoiceTextEntryValue-5]. | UK1: Q6.8. Are you disseminating or planning on disseminating the results of your research study [QID1318447236-ChoiceTextEntryValue-5] in the following ways? - Article in an academic journal | UL1: Q6.8. Are you disseminating or planning on disseminating the results of your research study [QID1318447236-ChoiceTextEntryValue-5] in the following ways? - Article in practitioner journal | UM1: Q6.8. Are you disseminating or planning on disseminating the results of your research study [QID1318447236-ChoiceTextEntryValue-5] in the following ways? - Article in a magazine | UN1: Q6.8. Are you disseminating or planning on disseminating the results of your research study [QID1318447236-ChoiceTextEntryValue-5] in the following ways? - Report available for free online (e.g., white paper or working paper) | UO1: Q6.8. Are you disseminating or planning on disseminating the results of your research study [QID1318447236-ChoiceTextEntryValue-5] in the following ways? - Conference presentation | UP1: Q6.8. Are you disseminating or planning on disseminating the results of your research study [QID1318447236-ChoiceTextEntryValue-5] in the following ways? - Blog or newsletter | UQ1: Q6.8. Are you disseminating or planning on disseminating the results of your research study [QID1318447236-ChoiceTextEntryValue-5] in the following ways? - Other (describe) | UR1: Q6.8. Are you disseminating or planning on disseminating the results of your research study [QID1318447236-ChoiceTextEntryValue-5] in the following ways? - Other (describe) - Text | US1: Q6.9. If any of your research results are published online for [QID1318447236-ChoiceTextEntryValue-5], please provide a URL: | UT1: Q6.3. Which of the following best describes the current stage of your study entitled [QID1318447236-ChoiceTextEntryValue-6]? | UU1: Q6.4. Briefly describe your primary research questions of your study entitled [QID1318447236-ChoiceTextEntryValue-6] (i.e., overarching questions that guide your research study, not specific data collection questions). | UV1: Q6.5. Who is the target population of your research study [QID1318447236-ChoiceTextEntryValue-6] (i.e., what population does your sample represent)? | UW1: Q6.6. Which of the following research designs are being used in your research study [QID1318447236-ChoiceTextEntryValue-6]? - Selected Choice - Descriptive (e.g., case study, naturalistic observation, survey) | UX1: Q6.6. Which of the following research designs are being used in your research study [QID1318447236-ChoiceTextEntryValue-6]? - Selected Choice - Correlational (e.g., case-control study, longitudinal analysis) | UY1: Q6.6. Which of the following research designs are being used in your research study [QID1318447236-ChoiceTextEntryValue-6]? - Selected Choice - Experimental or quasi-experimental | UZ1: Q6.6. Which of the following research designs are being used in your research study [QID1318447236-ChoiceTextEntryValue-6]? - Selected Choice - Review (e.g., literature review or systematic review) | VA1: Q6.6. Which of the following research designs are being used in your research study [QID1318447236-ChoiceTextEntryValue-6]? - Selected Choice - Meta-analytic | VB1: Q6.6. Which of the following research designs are being used in your research study [QID1318447236-ChoiceTextEntryValue-6]? - Selected Choice - Other (describe) | VC1: Q6.6. Which of the following research designs are being used in your research study [QID1318447236-ChoiceTextEntryValue-6]? - Other (describe) - Text | VD1: Q6.7. Briefly summarize the main results from your research study [QID1318447236-ChoiceTextEntryValue-6]. | VE1: Q6.8. Are you disseminating or planning on disseminating the results of your research study [QID1318447236-ChoiceTextEntryValue-6] in the following ways? - Article in an academic journal | VF1: Q6.8. Are you disseminating or planning on disseminating the results of your research study [QID1318447236-ChoiceTextEntryValue-6] in the following ways? - Article in practitioner journal | VG1: Q6.8. Are you disseminating or planning on disseminating the results of your research study [QID1318447236-ChoiceTextEntryValue-6] in the following ways? - Article in a magazine | VH1: Q6.8. Are you disseminating or planning on disseminating the results of your research study [QID1318447236-ChoiceTextEntryValue-6] in the following ways? - Report available for free online (e.g., white paper or working paper) | VI1: Q6.8. Are you disseminating or planning on disseminating the results of your research study [QID1318447236-ChoiceTextEntryValue-6] in the following ways? - Conference presentation | VJ1: Q6.8. Are you disseminating or planning on disseminating the results of your research study [QID1318447236-ChoiceTextEntryValue-6] in the following ways? - Blog or newsletter | VK1: Q6.8. Are you disseminating or planning on disseminating the results of your research study [QID1318447236-ChoiceTextEntryValue-6] in the following ways? - Other (describe) | VL1: Q6.8. Are you disseminating or planning on disseminating the results of your research study [QID1318447236-ChoiceTextEntryValue-6] in the following ways? - Other (describe) - Text | VM1: Q6.9. If any of your research results are published online for [QID1318447236-ChoiceTextEntryValue-6], please provide a URL: | VN1: Q6.3. Which of the following best describes the current stage of your study entitled [QID1318447236-ChoiceTextEntryValue-7]? | VO1: Q6.4. Briefly describe your primary research questions of your study entitled [QID1318447236-ChoiceTextEntryValue-7] (i.e., overarching questions that guide your research study, not specific data collection questions). | VP1: Q6.5. Who is the target population of your research study [QID1318447236-ChoiceTextEntryValue-7] (i.e., what population does your sample represent)? | VQ1: Q6.6. Which of the following research designs are being used in your research study [QID1318447236-ChoiceTextEntryValue-7]? - Selected Choice - Descriptive (e.g., case study, naturalistic observation, survey) | VR1: Q6.6. Which of the following research designs are being used in your research study [QID1318447236-ChoiceTextEntryValue-7]? - Selected Choice - Correlational (e.g., case-control study, longitudinal analysis) | VS1: Q6.6. Which of the following research designs are being used in your research study [QID1318447236-ChoiceTextEntryValue-7]? - Selected Choice - Experimental or quasi-experimental | VT1: Q6.6. Which of the following research designs are being used in your research study [QID1318447236-ChoiceTextEntryValue-7]? - Selected Choice - Review (e.g., literature review or systematic review) | VU1: Q6.6. Which of the following research designs are being used in your research study [QID1318447236-ChoiceTextEntryValue-7]? - Selected Choice - Meta-analytic | VV1: Q6.6. Which of the following research designs are being used in your research study [QID1318447236-ChoiceTextEntryValue-7]? - Selected Choice - Other (describe) | VW1: Q6.6. Which of the following research designs are being used in your research study [QID1318447236-ChoiceTextEntryValue-7]? - Other (describe) - Text | VX1: Q6.7. Briefly summarize the main results from your research study [QID1318447236-ChoiceTextEntryValue-7]. | VY1: Q6.8. Are you disseminating or planning on disseminating the results of your research study [QID1318447236-ChoiceTextEntryValue-7] in the following ways? - Article in an academic journal | VZ1: Q6.8. Are you disseminating or planning on disseminating the results of your research study [QID1318447236-ChoiceTextEntryValue-7] in the following ways? - Article in practitioner journal | WA1: Q6.8. Are you disseminating or planning on disseminating the results of your research study [QID1318447236-ChoiceTextEntryValue-7] in the following ways? - Article in a magazine | WB1: Q6.8. Are you disseminating or planning on disseminating the results of your research study [QID1318447236-ChoiceTextEntryValue-7] in the following ways? - Report available for free online (e.g., white paper or working paper) | WC1: Q6.8. Are you disseminating or planning on disseminating the results of your research study [QID1318447236-ChoiceTextEntryValue-7] in the following ways? - Conference presentation | WD1: Q6.8. Are you disseminating or planning on disseminating the results of your research study [QID1318447236-ChoiceTextEntryValue-7] in the following ways? - Blog or newsletter | WE1: Q6.8. Are you disseminating or planning on disseminating the results of your research study [QID1318447236-ChoiceTextEntryValue-7] in the following ways? - Other (describe) | WF1: Q6.8. Are you disseminating or planning on disseminating the results of your research study [QID1318447236-ChoiceTextEntryValue-7] in the following ways? - Other (describe) - Text | WG1: Q6.9. If any of your research results are published online for [QID1318447236-ChoiceTextEntryValue-7], please provide a URL: | WH1: Q6.3. Which of the following best describes the current stage of your study entitled [QID1318447236-ChoiceTextEntryValue-8]? | WI1: Q6.4. Briefly describe your primary research questions of your study entitled [QID1318447236-ChoiceTextEntryValue-8] (i.e., overarching questions that guide your research study, not specific data collection questions). | WJ1: Q6.5. Who is the target population of your research study [QID1318447236-ChoiceTextEntryValue-8] (i.e., what population does your sample represent)? | WK1: Q6.6. Which of the following research designs are being used in your research study [QID1318447236-ChoiceTextEntryValue-8]? - Selected Choice - Descriptive (e.g., case study, naturalistic observation, survey) | WL1: Q6.6. Which of the following research designs are being used in your research study [QID1318447236-ChoiceTextEntryValue-8]? - Selected Choice - Correlational (e.g., case-control study, longitudinal analysis) | WM1: Q6.6. Which of the following research designs are being used in your research study [QID1318447236-ChoiceTextEntryValue-8]? - Selected Choice - Experimental or quasi-experimental | WN1: Q6.6. Which of the following research designs are being used in your research study [QID1318447236-ChoiceTextEntryValue-8]? - Selected Choice - Review (e.g., literature review or systematic review) | WO1: Q6.6. Which of the following research designs are being used in your research study [QID1318447236-ChoiceTextEntryValue-8]? - Selected Choice - Meta-analytic | WP1: Q6.6. Which of the following research designs are being used in your research study [QID1318447236-ChoiceTextEntryValue-8]? - Selected Choice - Other (describe) | WQ1: Q6.6. Which of the following research designs are being used in your research study [QID1318447236-ChoiceTextEntryValue-8]? - Other (describe) - Text | WR1: Q6.7. Briefly summarize the main results from your research study [QID1318447236-ChoiceTextEntryValue-8]. | WS1: Q6.8. Are you disseminating or planning on disseminating the results of your research study [QID1318447236-ChoiceTextEntryValue-8] in the following ways? - Article in an academic journal | WT1: Q6.8. Are you disseminating or planning on disseminating the results of your research study [QID1318447236-ChoiceTextEntryValue-8] in the following ways? - Article in practitioner journal | WU1: Q6.8. Are you disseminating or planning on disseminating the results of your research study [QID1318447236-ChoiceTextEntryValue-8] in the following ways? - Article in a magazine | WV1: Q6.8. Are you disseminating or planning on disseminating the results of your research study [QID1318447236-ChoiceTextEntryValue-8] in the following ways? - Report available for free online (e.g., white paper or working paper) | WW1: Q6.8. Are you disseminating or planning on disseminating the results of your research study [QID1318447236-ChoiceTextEntryValue-8] in the following ways? - Conference presentation | WX1: Q6.8. Are you disseminating or planning on disseminating the results of your research study [QID1318447236-ChoiceTextEntryValue-8] in the following ways? - Blog or newsletter | WY1: Q6.8. Are you disseminating or planning on disseminating the results of your research study [QID1318447236-ChoiceTextEntryValue-8] in the following ways? - Other (describe) | WZ1: Q6.8. Are you disseminating or planning on disseminating the results of your research study [QID1318447236-ChoiceTextEntryValue-8] in the following ways? - Other (describe) - Text | XA1: Q6.9. If any of your research results are published online for [QID1318447236-ChoiceTextEntryValue-8], please provide a URL: | XB1: Q6.3. Which of the following best describes the current stage of your study entitled [QID1318447236-ChoiceTextEntryValue-9]? | XC1: Q6.4. Briefly describe your primary research questions of your study entitled [QID1318447236-ChoiceTextEntryValue-9] (i.e., overarching questions that guide your research study, not specific data collection questions). | XD1: Q6.5. Who is the target population of your research study [QID1318447236-ChoiceTextEntryValue-9] (i.e., what population does your sample represent)? | XE1: Q6.6. Which of the following research designs are being used in your research study [QID1318447236-ChoiceTextEntryValue-9]? - Selected Choice - Descriptive (e.g., case study, naturalistic observation, survey) | XF1: Q6.6. Which of the following research designs are being used in your research study [QID1318447236-ChoiceTextEntryValue-9]? - Selected Choice - Correlational (e.g., case-control study, longitudinal analysis) | XG1: Q6.6. Which of the following research designs are being used in your research study [QID1318447236-ChoiceTextEntryValue-9]? - Selected Choice - Experimental or quasi-experimental | XH1: Q6.6. Which of the following research designs are being used in your research study [QID1318447236-ChoiceTextEntryValue-9]? - Selected Choice - Review (e.g., literature review or systematic review) | XI1: Q6.6. Which of the following research designs are being used in your research study [QID1318447236-ChoiceTextEntryValue-9]? - Selected Choice - Meta-analytic | XJ1: Q6.6. Which of the following research designs are being used in your research study [QID1318447236-ChoiceTextEntryValue-9]? - Selected Choice - Other (describe) | XK1: Q6.6. Which of the following research designs are being used in your research study [QID1318447236-ChoiceTextEntryValue-9]? - Other (describe) - Text | XL1: Q6.7. Briefly summarize the main results from your research study [QID1318447236-ChoiceTextEntryValue-9]. | XM1: Q6.8. Are you disseminating or planning on disseminating the results of your research study [QID1318447236-ChoiceTextEntryValue-9] in the following ways? - Article in an academic journal | XN1: Q6.8. Are you disseminating or planning on disseminating the results of your research study [QID1318447236-ChoiceTextEntryValue-9] in the following ways? - Article in practitioner journal | XO1: Q6.8. Are you disseminating or planning on disseminating the results of your research study [QID1318447236-ChoiceTextEntryValue-9] in the following ways? - Article in a magazine | XP1: Q6.8. Are you disseminating or planning on disseminating the results of your research study [QID1318447236-ChoiceTextEntryValue-9] in the following ways? - Report available for free online (e.g., white paper or working paper) | XQ1: Q6.8. Are you disseminating or planning on disseminating the results of your research study [QID1318447236-ChoiceTextEntryValue-9] in the following ways? - Conference presentation | XR1: Q6.8. Are you disseminating or planning on disseminating the results of your research study [QID1318447236-ChoiceTextEntryValue-9] in the following ways? - Blog or newsletter | XS1: Q6.8. Are you disseminating or planning on disseminating the results of your research study [QID1318447236-ChoiceTextEntryValue-9] in the following ways? - Other (describe) | XT1: Q6.8. Are you disseminating or planning on disseminating the results of your research study [QID1318447236-ChoiceTextEntryValue-9] in the following ways? - Other (describe) - Text | XU1: Q6.9. If any of your research results are published online for [QID1318447236-ChoiceTextEntryValue-9], please provide a URL: | XV1: Publications Publications include articles, reports, white papers, or other documents of publishable quality or manuscripts intended for publication. Do not use this section of the survey to report on: Annual reports prepared for NSF. Evaluation reports. Conference presentations, roundtables, or posters. In 2023 did your ATE project develop articles, reports, or white papers for publication? | XW1: Q6.10. How many of each type of publication did your project develop in 2023? (If no publication was developed, put "0" in the corresponding box) - Manuscript for publication in academic journal - Total Number of Publications Developed | XX1: Q6.10. How many of each type of publication did your project develop in 2023? (If no publication was developed, put "0" in the corresponding box) - Manuscript for publication in practitioner journal - Total Number of Publications Developed | XY1: Q6.10. How many of each type of publication did your project develop in 2023? (If no publication was developed, put "0" in the corresponding box) - Report (not including evaluation reports or annual reports prepared for NSF... - Report (not including evaluation reports or annual reports prepared for NSF) - Total Number of Publications Developed | XZ1: Q6.10. How many of each type of publication did your project develop in 2023? (If no publication was developed, put "0" in the corresponding box) - Magazine article - Total Number of Publications Developed | YA1: Q6.10. How many of each type of publication did your project develop in 2023? (If no publication was developed, put "0" in the corresponding box) - Other (describe) - Text | YB1: Q6.10. How many of each type of publication did your project develop in 2023? (If no publication was developed, put "0" in the corresponding box) - Other (describe) - Total Number of Publications Developed | YC1: Coordination Network & Consortia A coordination network is a specific strategy for sharing information and ideas, fostering synthesis and new collaborations, developing common standards or industry-validated certifications, or otherwise advancing science and technician education through regular communication and sharing of ideas. Consortia for innovation is an ATE funding track that focuses on collaborations to strengthen partnerships between two-year institutions to advance education of the skilled technical workforce. Do not use this section of the survey to report on: Activities focused on communication among project partners. Informal or ad hoc interactions with colleagues. Professional networking or training events. In 2023, did your ATE project coordinate a network or a consortium to facilitate exchange or cooperation around research, training, or educational activities? | YD1: Q7.1. Was organizing a coordination network or consortium the primary purpose of your grant? | YE1: Q7.2. Briefly summarize the purpose of your coordination network(s) or consortium(s). | YF1: Q7.3. Briefly summarize the target audiences involved in your coordination network(s) or consortium(s). | YG1: Q7.4. Briefly summarize the intended outcomes of your coordination network(s) or consortium(s). | YH1: ATE Program Services and Support ATE program services involves the provision of activities, materials, or services to ATE program grantseekers, current grantees, and other participants and stakeholders to enhance their capacity to plan and conduct successful ATE projects. Do not use this section of the survey to report on: Discipline-specific activities that could be of interest to the ATE community. Research that could be of interest to the ATE community. Any other activities not specifically developed for ATE grantseekers and grantees. In 2023, did your ATE project provide services specifically for the ATE community? | YI1: Program Services Recode | YJ1: Q8.1. Did your project support the ATE community in the following ways? - Resource materials (e.g., guides, tutorials, videos) | YK1: Q8.1. Did your project support the ATE community in the following ways? - Workshops | YL1: Q8.1. Did your project support the ATE community in the following ways? - Webinars | YM1: Q8.1. Did your project support the ATE community in the following ways? - One-on-one technical assistance or advice | YN1: Q8.1. Did your project support the ATE community in the following ways? - Technical service (e.g., website hosting, webinar delivery, archiving) | YO1: Q8.1. Did your project support the ATE community in the following ways? - Other (describe) | YP1: Q8.1. Did your project support the ATE community in the following ways? - Other (describe) - Text | YQ1: Q8.2. How many workshops did your project provide in 2023? | YR1: Q8.3. On average, how many people attended per workshop? | YS1: Q8.4 How many webinars did your project provide in 2023? | YT1: Q8.5. On average, how many people attended per webinar? | YU1: Q8.6. How many people received one-on-one technical assistance or advice from your project in 2023? | YV1: Q9.1. For each type of collaborating organization listed below, report the number of different organizations you collaborated with in 2023. - Business/industry - Number of organizations | YW1: Q9.1. For each type of collaborating organization listed below, report the number of different organizations you collaborated with in 2023. - Within your host institution (not for grant management purposes) - Number of organizations | YX1: Q9.1. For each type of collaborating organization listed below, report the number of different organizations you collaborated with in 2023. - 2- or 4-year colleges - Number of organizations | YY1: Q9.1. For each type of collaborating organization listed below, report the number of different organizations you collaborated with in 2023. - K-12 schools or school system - Number of organizations | YZ1: Q9.1. For each type of collaborating organization listed below, report the number of different organizations you collaborated with in 2023. - Public agencies (e.g., government agencies) - Number of organizations | ZA1: Q9.1. For each type of collaborating organization listed below, report the number of different organizations you collaborated with in 2023. - Other ATE projects - Number of organizations | ZB1: Q9.1. For each type of collaborating organization listed below, report the number of different organizations you collaborated with in 2023. - Other (describe) - Text | ZC1: Q9.1. For each type of collaborating organization listed below, report the number of different organizations you collaborated with in 2023. - Other (describe) - Number of organizations | ZD1: Q9.2. What is the most important benefit your project derived from collaboration with all groups or organizations? | ZE1: Q9.3. Did your ATE project engage with individuals or groups from business and industry in any of the following ways in 2023? - Serve on an advisory board | ZF1: Q9.3. Did your ATE project engage with individuals or groups from business and industry in any of the following ways in 2023? - Review or advise on curriculum | ZG1: Q9.3. Did your ATE project engage with individuals or groups from business and industry in any of the following ways in 2023? - Provide educators with occupational experience and training (e.g., externships, mentoring, equipment access, demonstrations) | ZH1: Q9.3. Did your ATE project engage with individuals or groups from business and industry in any of the following ways in 2023? - Support business incubation or entrepreneurship | ZI1: Q9.3. Did your ATE project engage with individuals or groups from business and industry in any of the following ways in 2023? - Assist with instruction (e.g., guest lectures, classroom teaching, serve as panelists or judges, conduct site tours) | ZJ1: Q9.3. Did your ATE project engage with individuals or groups from business and industry in any of the following ways in 2023? - Provide monetary or in-kind support for program sustainability or enhancement (e.g., financial support, equipment donation, marketing assistance) | ZK1: Q9.3. Did your ATE project engage with individuals or groups from business and industry in any of the following ways in 2023? - Sponsor research | ZL1: Q9.3. Did your ATE project engage with individuals or groups from business and industry in any of the following ways in 2023? - Provide opportunities for workplace-based learning (e.g., internships, apprenticeships, co-op learning) | ZM1: Q9.3. Did your ATE project engage with individuals or groups from business and industry in any of the following ways in 2023? - Identify workforce needs | ZN1: Q9.4. What is the total dollar value of monetary and in-kind support received by your project from all sources other than your ATE award in 2023? - Monetary support - | ZO1: Q9.4. What is the total dollar value of monetary and in-kind support received by your project from all sources other than your ATE award in 2023? - In-kind support - | ZP1: Q9.4.1. Did your project receive the following in-kind support in 2023? - Staff time | ZQ1: Q9.4.1. Did your project receive the following in-kind support in 2023? - Equipment | ZR1: Q9.4.1. Did your project receive the following in-kind support in 2023? - Other (describe) | ZS1: Q9.4.1. Did your project receive the following in-kind support in 2023? - Other (describe) - Text | ZT1: Q9.5. How many hours did your advisory board meet in 2023? (round to the nearest hour) | ZU1: Q10.1. Did your project have an evaluator in 2023? | ZV1: Q10.2. Which type of evaluator(s) did your project have in 2023? | ZW1: Q10.2.1. How frequently did your external evaluator interact with your project's staff (e.g., by email, teleconference, face-to-face) in 2023? | ZX1: Q10.3 What type of report(s) did you receive from your evaluator in 2023? | ZY1: Q10.4. If you have any information related to the evaluation of your project online (e.g., plans, instruments, reports), please provide the URL where they can be located: - Selected Choice | ZZ1: Q10.4. If you have any information related to the evaluation of your project online (e.g., plans, instruments, reports), please provide the URL where they can be located: - Online location of evaluation reports: - Text | AAA1: Q10.5. Have your project's evaluation findings or your work with an evaluator caused you to make any of the following changes to your ATE project in 2023? (Please select all that apply.) - Selected Choice - Alter the timing of project activities | AAB1: Q10.5. Have your project's evaluation findings or your work with an evaluator caused you to make any of the following changes to your ATE project in 2023? (Please select all that apply.) - Selected Choice - Change the content of curriculum or training materials | AAC1: Q10.5. Have your project's evaluation findings or your work with an evaluator caused you to make any of the following changes to your ATE project in 2023? (Please select all that apply.) - Selected Choice - Start, stop, or add project activities | AAD1: Q10.5. Have your project's evaluation findings or your work with an evaluator caused you to make any of the following changes to your ATE project in 2023? (Please select all that apply.) - Selected Choice - Modify project goals or objectives (e.g. adding or eliminating project goals) | AAE1: Q10.5. Have your project's evaluation findings or your work with an evaluator caused you to make any of the following changes to your ATE project in 2023? (Please select all that apply.) - Selected Choice - Modify the target audience for project activities | AAF1: Q10.5. Have your project's evaluation findings or your work with an evaluator caused you to make any of the following changes to your ATE project in 2023? (Please select all that apply.) - Selected Choice - Redesign marketing, recruitment, or outreach activities (aimed at sutdents, faculty, or industry) | AAG1: Q10.5. Have your project's evaluation findings or your work with an evaluator caused you to make any of the following changes to your ATE project in 2023? (Please select all that apply.) - Selected Choice - Other (describe) | AAH1: Q10.5. Have your project's evaluation findings or your work with an evaluator caused you to make any of the following changes to your ATE project in 2023? (Please select all that apply.) - Other (describe) - Text | AAI1: 10.6 Have your project’s evaluation findings or your work with an evaluator caused you to engage in any of the following in 2023? (Please select all that apply) - Selected Choice - Advocate for change within your program or institution? | AAJ1: 10.6 Have your project’s evaluation findings or your work with an evaluator caused you to engage in any of the following in 2023? (Please select all that apply) - Selected Choice - Apply for another ATE grant | AAK1: 10.6 Have your project’s evaluation findings or your work with an evaluator caused you to engage in any of the following in 2023? (Please select all that apply) - Selected Choice - Learn more about the evaluation field or evaluation approaches or practices | AAL1: 10.6 Have your project’s evaluation findings or your work with an evaluator caused you to engage in any of the following in 2023? (Please select all that apply) - Selected Choice - Change the way non-ATE projects or work are implemented | AAM1: 10.6 Have your project’s evaluation findings or your work with an evaluator caused you to engage in any of the following in 2023? (Please select all that apply) - Selected Choice - Other (describe) | AAN1: 10.6 Have your project’s evaluation findings or your work with an evaluator caused you to engage in any of the following in 2023? (Please select all that apply) - Other (describe) - Text | AAO1: Q10.7. With whom have you shared your current project's evaluation results? (If a group does not apply to your project, select "NA" for not applicable.) - NSF program officer | AAP1: Q10.7. With whom have you shared your current project's evaluation results? (If a group does not apply to your project, select "NA" for not applicable.) - Project advisory committee | AAQ1: Q10.7. With whom have you shared your current project's evaluation results? (If a group does not apply to your project, select "NA" for not applicable.) - Executive administrators in your organization (e.g., CEO, president, vice president, dean, department chairperson) | AAR1: Q10.7. With whom have you shared your current project's evaluation results? (If a group does not apply to your project, select "NA" for not applicable.) - Faculty or staff at your project's host institution | AAS1: Q10.7. With whom have you shared your current project's evaluation results? (If a group does not apply to your project, select "NA" for not applicable.) - Current project partners | AAT1: Q10.7. With whom have you shared your current project's evaluation results? (If a group does not apply to your project, select "NA" for not applicable.) - Prospective project partners | AAU1: Q10.7. With whom have you shared your current project's evaluation results? (If a group does not apply to your project, select "NA" for not applicable.) - Prospective students or parents | AAV1: Q10.7. With whom have you shared your current project's evaluation results? (If a group does not apply to your project, select "NA" for not applicable.) - Educators or professionals outside of your project and institution (e.g., at conferences, in journals, or during webinars) | AAW1: Q10.7. With whom have you shared your current project's evaluation results? (If a group does not apply to your project, select "NA" for not applicable.) - Other (describe) | AAX1: Q10.7. With whom have you shared your current project's evaluation results? (If a group does not apply to your project, select "NA" for not applicable.) - Other (describe) - Text | AAY1: 10.8 How would you rate the usefulness of your project's interaction with your current evaluator? | AAZ1: 10.8.1 In a few sentences, please describe why your interaction with your evaluator was [QID638-ChoiceDescription-1]. (Your responses will not be shared with your evaluator or NSF program officer and will only be reported in the aggregate or de-identified.) | ABA1: 10.8.1 In a few sentences, please describe why your interaction with your evaluator was [QID638-ChoiceDescription-2]. (Your responses will not be shared with your evaluator or NSF program officer and will only be reported in the aggregate or de-identified.) | ABB1: 10.8.1 In a few sentences, please describe why your interaction with your evaluator was [QID638-ChoiceDescription-3]. (Your responses will not be shared with your evaluator or NSF program officer and will only be reported in the aggregate or de-identified.) | ABC1: 10.8.1 In a few sentences, please describe why your interaction with your evaluator was [QID638-ChoiceDescription-4]. (Your responses will not be shared with your evaluator or NSF program officer and will only be reported in the aggregate or de-identified.) | ABD1: Q10.9 How would you rate the usefulness of the evaluation findings to your project? | ABE1: 10.9.1. In a few sentences, please describe why your evaluation findings were [QID640-ChoiceDescription-1]. (Your responses will not be shared with your evaluator or NSF program officer and will only be reported in the aggregate or de-identified.) | ABF1: 10.9.1. In a few sentences, please describe why your evaluation findings were [QID640-ChoiceDescription-2]. (Your responses will not be shared with your evaluator or NSF program officer and will only be reported in the aggregate or de-identified.) | ABG1: 10.9.1. In a few sentences, please describe why your evaluation findings were [QID640-ChoiceDescription-3]. (Your responses will not be shared with your evaluator or NSF program officer and will only be reported in the aggregate or de-identified.) | ABH1: 10.9.1. In a few sentences, please describe why your evaluation findings were [QID640-ChoiceDescription-4]. (Your responses will not be shared with your evaluator or NSF program officer and will only be reported in the aggregate or de-identified.) | ABI1: Q10.10. What is your primary evaluator's name, email, and organizational affiliation (e.g., Jane Smith, jane.smith@wmich.edu, Western Michigan University)? - Evaluator's first and last name | ABJ1: Q10.10. What is your primary evaluator's name, email, and organizational affiliation (e.g., Jane Smith, jane.smith@wmich.edu, Western Michigan University)? - Evaluator email address | ABK1: Q10.10. What is your primary evaluator's name, email, and organizational affiliation (e.g., Jane Smith, jane.smith@wmich.edu, Western Michigan University)? - Organizational affiliation | ABL1: Q10.11. Are there additional evaluators on your evaluation team? | ABM1: Q10.11.1. Please provide additional evaluator name(s), email address(es), and organizational affiliation(s). - Evaluator first and last name | ABN1: Q10.11.1. Please provide additional evaluator name(s), email address(es), and organizational affiliation(s). - Evaluator email address | ABO1: Q10.11.1. Please provide additional evaluator name(s), email address(es), and organizational affiliation(s). - Organizational affiliation | ABP1: Q10.11.1. Please provide additional evaluator name(s), email address(es), and organizational affiliation(s). - Evaluator first and last name | ABQ1: Q10.11.1. Please provide additional evaluator name(s), email address(es), and organizational affiliation(s). - Evaluator email address | ABR1: Q10.11.1. Please provide additional evaluator name(s), email address(es), and organizational affiliation(s). - Organizational affiliation | ABS1: Q10.11.1. Please provide additional evaluator name(s), email address(es), and organizational affiliation(s). - Evaluator first and last name | ABT1: Q10.11.1. Please provide additional evaluator name(s), email address(es), and organizational affiliation(s). - Evaluator email address | ABU1: Q10.11.1. Please provide additional evaluator name(s), email address(es), and organizational affiliation(s). - Organizational affiliation | ABV1: Q10.11.1. Please provide additional evaluator name(s), email address(es), and organizational affiliation(s). - Evaluator first and last name | ABW1: Q10.11.1. Please provide additional evaluator name(s), email address(es), and organizational affiliation(s). - Evaluator email address | ABX1: Q10.11.1. Please provide additional evaluator name(s), email address(es), and organizational affiliation(s). - Organizational affiliation | ABY1: 10.12. How long has your ATE project worked with this evaluator (or evaluation team)? | ABZ1: Q10.13. Has your team worked with this evaluator (or evaluation team) on previous ATE or non-ATE grants? | ACA1: Q10.14. EvaluATE is working with ATE Central to make information about ATE evaluators available on the ATE Central website (www.atecentral.net). If [QID135-ChoiceTextEntryValue-1] approves, may we identify them as your evaluator on the ATE Central website? | ACB1: Q10.1.a. Why did you not work with an evaluator in 2023? | ACC1: Q11.1. What was your project's most important achievement in 2023? | ACD1: Q11.1.1. Did you gather data about this achievement? | ACE1: Q11.1.1.a. What kind of data and how was it collected? | ACF1: Q11.2. What are one or two promising practices from your ATE work that can be shared with the ATE community? | ACG1: Q.1. Does your project include an extended reality technology component? | ACH1: Q.2. Which of the following are reasons why your project does not include an extended reality technology component? (Please select all that apply.) - Selected Choice - Not relevant to my ATE project | ACI1: Q.2. Which of the following are reasons why your project does not include an extended reality technology component? (Please select all that apply.) - Selected Choice - Don't know enough about it | ACJ1: Q.2. Which of the following are reasons why your project does not include an extended reality technology component? (Please select all that apply.) - Selected Choice - Extended reality hardware is too expensive | ACK1: Q.2. Which of the following are reasons why your project does not include an extended reality technology component? (Please select all that apply.) - Selected Choice - Extended reality content is too expensive | ACL1: Q.2. Which of the following are reasons why your project does not include an extended reality technology component? (Please select all that apply.) - Selected Choice - Lack of physical space to house and use extended reality technologies | ACM1: Q.2. Which of the following are reasons why your project does not include an extended reality technology component? (Please select all that apply.) - Selected Choice - Insufficient time for staff to learn and/or integrate extended reality technologies | ACN1: Q.2. Which of the following are reasons why your project does not include an extended reality technology component? (Please select all that apply.) - Selected Choice - Lack of support by college administrators | ACO1: Q.2. Which of the following are reasons why your project does not include an extended reality technology component? (Please select all that apply.) - Selected Choice - Lack of relevant extended reality content | ACP1: Q.2. Which of the following are reasons why your project does not include an extended reality technology component? (Please select all that apply.) - Selected Choice - Other (describe) | ACQ1: Q.2. Which of the following are reasons why your project does not include an extended reality technology component? (Please select all that apply.) - Other (describe) - Text | ACR1: Q.3. For each reason selected, indicate how much of a barrier it is to your project's inclusion of extended reality technologies. - Not relevant to my ATE project | ACS1: Q.3. For each reason selected, indicate how much of a barrier it is to your project's inclusion of extended reality technologies. - Don't know enough about it | ACT1: Q.3. For each reason selected, indicate how much of a barrier it is to your project's inclusion of extended reality technologies. - Extended reality hardware is too expensive | ACU1: Q.3. For each reason selected, indicate how much of a barrier it is to your project's inclusion of extended reality technologies. - Extended reality content is too expensive | ACV1: Q.3. For each reason selected, indicate how much of a barrier it is to your project's inclusion of extended reality technologies. - Lack of physical space to house and use extended reality technologies | ACW1: Q.3. For each reason selected, indicate how much of a barrier it is to your project's inclusion of extended reality technologies. - Insufficient time for staff to learn and/or integrate extended reality technologies | ACX1: Q.3. For each reason selected, indicate how much of a barrier it is to your project's inclusion of extended reality technologies. - Lack of support by college administrators | ACY1: Q.3. For each reason selected, indicate how much of a barrier it is to your project's inclusion of extended reality technologies. - Lack of relevant extended reality content | ACZ1: Q.3. For each reason selected, indicate how much of a barrier it is to your project's inclusion of extended reality technologies. - Other (describe) | ADA1: Q.3. For each reason selected, indicate how much of a barrier it is to your project's inclusion of extended reality technologies. - Other (describe) - Text | ADB1: Q.4. Would your project like assistance incorporating extended reality technologies into your ATE project? | ADC1: Q.2. For what purpose(s) does your project use extended reality technologies? (Please select all that apply.) - Selected Choice - Company tours | ADD1: Q.2. For what purpose(s) does your project use extended reality technologies? (Please select all that apply.) - Selected Choice - Teaching abstract concepts | ADE1: Q.2. For what purpose(s) does your project use extended reality technologies? (Please select all that apply.) - Selected Choice - Developing hands-on skills | ADF1: Q.2. For what purpose(s) does your project use extended reality technologies? (Please select all that apply.) - Selected Choice - Improving responses to realistic scenarios (e.g., emergency response, soft skills training) | ADG1: Q.2. For what purpose(s) does your project use extended reality technologies? (Please select all that apply.) - Selected Choice - Training on machines (e.g., expensive and/or inaccessible equipment, safety training) | ADH1: Q.2. For what purpose(s) does your project use extended reality technologies? (Please select all that apply.) - Selected Choice - Other (describe) | ADI1: Q.2. For what purpose(s) does your project use extended reality technologies? (Please select all that apply.) - Other (describe) - Text | ADJ1: Q.3. How is your project obtaining the extended reality content it is using? - Company tours | ADK1: Q.3. How is your project obtaining the extended reality content it is using? - Teaching abstract concepts | ADL1: Q.3. How is your project obtaining the extended reality content it is using? - Developing hands-on skills | ADM1: Q.3. How is your project obtaining the extended reality content it is using? - Improving responses to realistic scenarios (e.g., emergency response, soft skills training) | ADN1: Q.3. How is your project obtaining the extended reality content it is using? - Training on machines (e.g., expensive and/or inaccessible equipment, safety training) | ADO1: Q.3. How is your project obtaining the extended reality content it is using? - [QID613-ChoiceTextEntryValue-6] | ADP1: Q.4. Which of these extended reality technologies are a part of your project? (Please select all that apply.) - Selected Choice - AR - tablet/smartphone | ADQ1: Q.4. Which of these extended reality technologies are a part of your project? (Please select all that apply.) - Selected Choice - AR - clear lenses | ADR1: Q.4. Which of these extended reality technologies are a part of your project? (Please select all that apply.) - Selected Choice - AR - passthrough | ADS1: Q.4. Which of these extended reality technologies are a part of your project? (Please select all that apply.) - Selected Choice - VR - desktop only | ADT1: Q.4. Which of these extended reality technologies are a part of your project? (Please select all that apply.) - Selected Choice - VR - head-mounted display only | ADU1: Q.4. Which of these extended reality technologies are a part of your project? (Please select all that apply.) - Selected Choice - VR - desktop combined with head-mounted display | ADV1: Q.4. Which of these extended reality technologies are a part of your project? (Please select all that apply.) - Selected Choice - Other (describe) | ADW1: Q.4. Which of these extended reality technologies are a part of your project? (Please select all that apply.) - Other (describe) - Text | ADX1: Q.5. Would you be willing to discuss these topics further with the RECITE research team? | ADY1: Q.6. Would your ATE project like assistance incorporating extended reality technologies? | ADZ1: Q.1. Does your project include a professional development component? | AEA1: Q.2. What types of professional development opportunities has your project developed? (Please select all that apply.) - Selected Choice - Online course(s) | AEB1: Q.2. What types of professional development opportunities has your project developed? (Please select all that apply.) - Selected Choice - Face-to-face course(s) | AEC1: Q.2. What types of professional development opportunities has your project developed? (Please select all that apply.) - Selected Choice - Hybrid course(s) | AED1: Q.2. What types of professional development opportunities has your project developed? (Please select all that apply.) - Selected Choice - Massive Open Online Course(s) (MOOC) | AEE1: Q.2. What types of professional development opportunities has your project developed? (Please select all that apply.) - Selected Choice - Conference(s) | AEF1: Q.2. What types of professional development opportunities has your project developed? (Please select all that apply.) - Selected Choice - Webinar(s) | AEG1: Q.2. What types of professional development opportunities has your project developed? (Please select all that apply.) - Selected Choice - Other (describe) | AEH1: Q.2. What types of professional development opportunities has your project developed? (Please select all that apply.) - Other (describe) - Text | AEI1: Q.3. How often has your project implemented each professional development opportunity? - Online course(s) | AEJ1: Q.3. How often has your project implemented each professional development opportunity? - Face-to-face course(s) | AEK1: Q.3. How often has your project implemented each professional development opportunity? - Hybrid course(s) | AEL1: Q.3. How often has your project implemented each professional development opportunity? - Massive Open Online Course(s) (MOOC) | AEM1: Q.3. How often has your project implemented each professional development opportunity? - Conference(s) | AEN1: Q.3. How often has your project implemented each professional development opportunity? - Webinar(s) | AEO1: Q.3. How often has your project implemented each professional development opportunity? - [QID621-ChoiceTextEntryValue-7] | AEP1: Q.4. What barriers has your project encountered while implementing professional development? (Please select all that apply.) - Selected Choice - Finding NSF ATE community partners | AEQ1: Q.4. What barriers has your project encountered while implementing professional development? (Please select all that apply.) - Selected Choice - Finding non-NSF ATE community partners | AER1: Q.4. What barriers has your project encountered while implementing professional development? (Please select all that apply.) - Selected Choice - Communication with participants | AES1: Q.4. What barriers has your project encountered while implementing professional development? (Please select all that apply.) - Selected Choice - Implementation costs | AET1: Q.4. What barriers has your project encountered while implementing professional development? (Please select all that apply.) - Selected Choice - Participant costs | AEU1: Q.4. What barriers has your project encountered while implementing professional development? (Please select all that apply.) - Selected Choice - Institutional barriers on the ATE project's campus | AEV1: Q.4. What barriers has your project encountered while implementing professional development? (Please select all that apply.) - Selected Choice - Institutional barriers on participants' campus | AEW1: Q.4. What barriers has your project encountered while implementing professional development? (Please select all that apply.) - Selected Choice - Other (describe) | AEX1: Q.4. What barriers has your project encountered while implementing professional development? (Please select all that apply.) - Other (describe) - Text | AEY1: Q.5. Please rate the level of significance of each barrier below as it relates to the implementation of your project's professional development activities. - Finding NSF ATE community partners | AEZ1: Q.5. Please rate the level of significance of each barrier below as it relates to the implementation of your project's professional development activities. - Finding non-NSF ATE community partners | AFA1: Q.5. Please rate the level of significance of each barrier below as it relates to the implementation of your project's professional development activities. - Communication with participants | AFB1: Q.5. Please rate the level of significance of each barrier below as it relates to the implementation of your project's professional development activities. - Implementation costs | AFC1: Q.5. Please rate the level of significance of each barrier below as it relates to the implementation of your project's professional development activities. - Participant costs | AFD1: Q.5. Please rate the level of significance of each barrier below as it relates to the implementation of your project's professional development activities. - Institutional barriers on my campus | AFE1: Q.5. Please rate the level of significance of each barrier below as it relates to the implementation of your project's professional development activities. - Institutional barriers on participants' campus | AFF1: Q.5. Please rate the level of significance of each barrier below as it relates to the implementation of your project's professional development activities. - [QID623-ChoiceTextEntryValue-9] | AFG1: Q.6. What avenues has your project used to recruit participants for professional development activities? (Please select all that apply.) - Selected Choice - Newsletters | AFH1: Q.6. What avenues has your project used to recruit participants for professional development activities? (Please select all that apply.) - Selected Choice - Flyers | AFI1: Q.6. What avenues has your project used to recruit participants for professional development activities? (Please select all that apply.) - Selected Choice - Website | AFJ1: Q.6. What avenues has your project used to recruit participants for professional development activities? (Please select all that apply.) - Selected Choice - Direct email to potential participants | AFK1: Q.6. What avenues has your project used to recruit participants for professional development activities? (Please select all that apply.) - Selected Choice - System/administration-forwarded email | AFL1: Q.6. What avenues has your project used to recruit participants for professional development activities? (Please select all that apply.) - Selected Choice - Face-to-face communication | AFM1: Q.6. What avenues has your project used to recruit participants for professional development activities? (Please select all that apply.) - Selected Choice - Referrals | AFN1: Q.6. What avenues has your project used to recruit participants for professional development activities? (Please select all that apply.) - Selected Choice - Departmental or school communications | AFO1: Q.6. What avenues has your project used to recruit participants for professional development activities? (Please select all that apply.) - Selected Choice - Facebook | AFP1: Q.6. What avenues has your project used to recruit participants for professional development activities? (Please select all that apply.) - Selected Choice - LinkedIn | AFQ1: Q.6. What avenues has your project used to recruit participants for professional development activities? (Please select all that apply.) - Selected Choice - TikTok | AFR1: Q.6. What avenues has your project used to recruit participants for professional development activities? (Please select all that apply.) - Selected Choice - Instagram | AFS1: Q.6. What avenues has your project used to recruit participants for professional development activities? (Please select all that apply.) - Selected Choice - X (Twitter) | AFT1: Q.6. What avenues has your project used to recruit participants for professional development activities? (Please select all that apply.) - Selected Choice - Contracted professional communications team | AFU1: Q.6. What avenues has your project used to recruit participants for professional development activities? (Please select all that apply.) - Selected Choice - Professional communications team member | AFV1: Q.6. What avenues has your project used to recruit participants for professional development activities? (Please select all that apply.) - Selected Choice - Other (describe) | AFW1: Q.6. What avenues has your project used to recruit participants for professional development activities? (Please select all that apply.) - Other (describe) - Text | AFX1: Q.7. Please rate the success level of each strategy used to recruit participants for professional development activities. - Newsletters | AFY1: Q.7. Please rate the success level of each strategy used to recruit participants for professional development activities. - Flyers | AFZ1: Q.7. Please rate the success level of each strategy used to recruit participants for professional development activities. - Website | AGA1: Q.7. Please rate the success level of each strategy used to recruit participants for professional development activities. - Direct email to potential participants | AGB1: Q.7. Please rate the success level of each strategy used to recruit participants for professional development activities. - System-Administration forwarded email | AGC1: Q.7. Please rate the success level of each strategy used to recruit participants for professional development activities. - Face-to-face communication | AGD1: Q.7. Please rate the success level of each strategy used to recruit participants for professional development activities. - Referrals | AGE1: Q.7. Please rate the success level of each strategy used to recruit participants for professional development activities. - Departmental or School communications | AGF1: Q.7. Please rate the success level of each strategy used to recruit participants for professional development activities. - Facebook | AGG1: Q.7. Please rate the success level of each strategy used to recruit participants for professional development activities. - LinkedIn | AGH1: Q.7. Please rate the success level of each strategy used to recruit participants for professional development activities. - TikTok | AGI1: Q.7. Please rate the success level of each strategy used to recruit participants for professional development activities. - Instagram | AGJ1: Q.7. Please rate the success level of each strategy used to recruit participants for professional development activities. - X (Twitter) | AGK1: Q.7. Please rate the success level of each strategy used to recruit participants for professional development activities. - Contracted professional communications team | AGL1: Q.7. Please rate the success level of each strategy used to recruit participants for professional development activities. - Professional communications team member | AGM1: Q.7. Please rate the success level of each strategy used to recruit participants for professional development activities. - [QID625-ChoiceTextEntryValue-16] | AGN1: Q.8. How prepared was your team to create recruitment materials for professional development activities? | AGO1: Q.9. How prepared was your team to disseminate recruitment materials for professional development activities? | AGP1: Q.10. What percentage of your professional development participants would you estimate are currently involved with an active NSF ATE project? - Percentage working with active NSF ATE project | AGQ1: Q.1. Did your team receive some kind of external mentoring support or assistance while developing the proposal for [Field-Awd_Title]? | AGR1: Q.1.1. Please indicate the type of support received while developing the proposal for [Field-Awd_Title]. (Please select all that apply) - Selected Choice - Support from an ATE mentoring project organization (e.g., Mentor-Connect, Mentor Up, MentorLinks, FORCCE-ATE, Project Vision, Grant-Seeker Academy) | AGS1: Q.1.1. Please indicate the type of support received while developing the proposal for [Field-Awd_Title]. (Please select all that apply) - Selected Choice - Support from an ATE center | AGT1: Q.1.1. Please indicate the type of support received while developing the proposal for [Field-Awd_Title]. (Please select all that apply) - Selected Choice - Support from an independent grant writing consultant company | AGU1: Q.1.1. Please indicate the type of support received while developing the proposal for [Field-Awd_Title]. (Please select all that apply) - Selected Choice - Other (describe) | AGV1: Q.1.1. Please indicate the type of support received while developing the proposal for [Field-Awd_Title]. (Please select all that apply) - Other (describe) - Text | AGW1: Q.1.1.a. Which ATE mentoring project organization helped you? (Please select all that apply.) - Selected Choice - Mentor-Connect | AGX1: Q.1.1.a. Which ATE mentoring project organization helped you? (Please select all that apply.) - Selected Choice - Mentor Up | AGY1: Q.1.1.a. Which ATE mentoring project organization helped you? (Please select all that apply.) - Selected Choice - MentorLinks | AGZ1: Q.1.1.a. Which ATE mentoring project organization helped you? (Please select all that apply.) - Selected Choice - FORCCE-ATE | AHA1: Q.1.1.a. Which ATE mentoring project organization helped you? (Please select all that apply.) - Selected Choice - Project Vision | AHB1: Q.1.1.a. Which ATE mentoring project organization helped you? (Please select all that apply.) - Selected Choice - Grant-Seeker Academy | AHC1: Q.1.1.a. Which ATE mentoring project organization helped you? (Please select all that apply.) - Selected Choice - Other (describe) | AHD1: Q.1.1.a. Which ATE mentoring project organization helped you? (Please select all that apply.) - Other (describe) - Text | AHE1: Q.1.1.b. Which ATE center helped you? | AHF1: Q.1.1.c. Which independent grant writing consultant or company helped you? | AHG1: Q.2. Would you have applied to the NSF ATE program without that mentoring or assistance? | AHH1: Q.3. Do you anticipate applying for another NSF ATE proposal? | AHI1: Q.3.1. Please briefly explain why you answered [QID1318571236-ChoiceDescription-1] to the previous question. | AHJ1: Q.3.1. Please briefly explain why you answered [QID1318571236-ChoiceDescription-2] to the previous question. | AHK1: Q.3.1. Please briefly explain why you answered [QID1318571236-ChoiceDescription-3] to the previous question. | AHL1: Q.3.1. Please briefly explain why you answered [QID1318571236-ChoiceDescription-4] to the previous question. | AHM1: Q.3.1. Please briefly explain why you answered [QID1318571236-ChoiceDescription-5] to the previous question. | AHN1: Q.4. Would you be willing to discuss these topics further with the research team? | AHO1: Did you respond "Yes" to at least one activity? | AHP1: Did you respond "no" to all activities? | AHQ1: Did you respond "planning to" to all activities | AHV1: 1
A2: 2400825 | B2: Electric Vehicle Education for New Jersey (EVE-NJ) | C2: 1 | D2: 0 | E2: 1 | F2: 2 | G2: 1 | H2: 2 | J2: 1 | K2: 1 | T2: =COUNTIF(K2:S2,1) -> 1 | U2: https://www.brookdalecc.edu/brookdale-receives-grant-from-national-science-foundation-to-launch-electric-vehicle-program-in-automotive-department/ | V2: 3 | W2: 561318 | X2: 1 | AF2: 1 | AG2: 1 | AH2: 1 | AP2: 1 | AQ2: 2 | BA2: 2 | BB2: 6 | BD2: 6 | BE2: 1 | BG2: 4 | BH2: 3 | FI2: 3 | JG2: 2 | JP2: 3 | JQ2: 2 | LL2: 1 | LM2: 55000 | LN2: 1 | LP2: 0 | LQ2: 0 | LR2: 4 | LS2: It has not yet, but it will expand on their knowledge of Electric Vehicle operation and repair. | LT2: 2 | ME2: 2 | OG2: 2 | OS2: 2 | OV2: 2 | PM2: 2 | PN2: 1 | QA2: Global Electric Vehicle Certifications - EVPRO+ Program; authenticated by SAE-ITC | QB2: 2 | QC2: 2 | QE2: 3 | RO2: 2 | SC2: 2 | XV2: 2 | YC2: 2 | YH2: 2 | YV2: 15 | YW2: 50 | YX2: 10 | YY2: 4 | YZ2: 5 | ZE2: 1 | ZF2: 3 | ZG2: 1 | ZH2: 2 | ZI2: 2 | ZJ2: 2 | ZK2: 2 | ZL2: 1 | ZM2: 1 | ZN2: 97000 | ZO2: 0 | ZT2: 1 | ZU2: 1 | ZV2: 1 | ZW2: 3 | ZX2: 4 | AAY2: 3 | ABB2: Our Evaluator has been in touch with us in person, email, Zoom, and on the phone. She has been great for guidance and feedback, and as we move through this, we should have some very good reports in the future. | ABD2: 4 | ABH2: She provided us guidance when we needed it. She helped us clarify our purpose and direction on where we should be going with some of our components of our project. | ABI2: Cameron Craft | ABJ2: egscollaborative@gmail.com | ABK2: EGS Collaborative | ABL2: 2 | ABY2: 1 | ABZ2: 2 | ACA2: 1 | ACC2: Becoming EVPRO+ Level 1 Certified which is a Global Certification | ACD2: 2 | ACF2: We are still developing our practices. | ACG2: 2 | ACP2: 1 | ACQ2: each of the 15 colleges have multiple resources, NEVTEX-Next does not prescribe | ACZ2: 1 | ADB2: 2 | AGQ2: 1 | AGR2: 1 | AGW2: 1 | AHG2: 4 | AHH2: 5 | AHM2: Still looking at the current project for results. In discussion about the future of NSF ATE with EV technologies. | AHN2: 1 | AHO2: =OR($YH2=1,$YC2=1,$XV2=1,$SC2=1,$RO2=1,$QE2=1,$PM2=1,$OV2=1,$OS2=1,$OG2=1,$ME2=1,$LT2=1,$LL2=1,$JQ2=1,$JP2=1,$JG2=1,$FI2=1,$BH2=1) -> TRUE | AHP2: =AND($YH2=2,$YC2=2,$XV2=2,$SC2=2,$RO2=2,$QE2=2,$PM2=2,$OV2=2,$OS2=2,$OG2=2,$ME2=2,$LT2=2,$LL2=2,$JQ2=2,$JP2=2,$JG2=2,$FI2=2,$BH2=2) -> FALSE | AHQ2: =AND($YH2=3,$YC2=3,$XV2=3,$SC2=3,$RO2=3,$QE2=3,$PM2=3,$OV2=3,$OS2=3,$OG2=3,$ME2=3,$LT2=3,$LL2=3,$JQ2=3,$JP2=3,$JG2=3,$FI2=3,$BH2=3) -> FALSE
A3: 2026262 | B3: The Hidden Innovation Infrastructure: Understanding the Economic Development Role of Technician Education in the Changing Future of Work | C3: 7 | D3: 0 | E3: 2 | F3: 0 | G3: 1 | H3: 1 | J3: 2 | T3: =COUNTIF(K3:S3,1) -> 0 | U3: https://sites.rutgers.edu/eerc-hii/ | V3: 4 | W3: 1907954 | X3: 39 | AE3: Research on technician education | AF3: 8 | AG3: 1 | AH3: 2 | AP3: 1 | AQ3: 1 | AR3: 4 | AS3: 1 | AT3: 1 | AU3: 1 | AW3: 1 | BA3: 2 | BB3: 4 | BD3: 4 | BE3: 2 | BG3: 4 | BH3: 2 | BI3: 2 | BO3: 1 | BP3: 2 | BT3: 3 | EV3: 2 | EW3: 2 | FI3: 2 | JG3: 2 | JP3: 2 | JQ3: 1 | KN3: 2 | KO3: 2 | KP3: 2 | KQ3: 2 | KR3: 2 | KS3: 2 | KT3: 2 | KU3: 2 | KV3: 2 | KW3: 2 | KX3: 2 | KY3: 1 | KZ3: Research reports, briefs | LA3: 2 | LB3: 1 | LC3: 1 | LD3: 2 | LE3: 1 | LF3: 2 | LL3: 2 | LT3: 2 | ME3: 2 | OG3: 2 | OS3: 2 | OV3: 2 | PM3: 2 | PN3: 4 | QE3: 2 | RO3: 2 | SC3: 1 | SD3: 2 | SE3: Case studies on the economic development role of community college technician education | SF3: Surveys of manufacturing employers and hiring of community college technicians | SL3: 4 | SM3: How are community college technician education programs engaged in the regional economic development ecosystem? | SN3: 8 colleges in 4 states, focused on community college manufacturing programs | SO3: 1 | SV3: Colleges and their technician programs are engaged in economic development activities through a range of activities that seek to serve the broader economic health of their regions in addition to meeting student needs and serving the needs of business. | SW3: 1 | SX3: 1 | SY3: 1 | SZ3: 1 | TA3: 1 | TB3: 1 | TF3: 2 | TG3: How do hiring managers in manufacturing firms perceive and engage with their local community college technician programs? | TH3: Manufacturers in the areas surrounding the 8 colleges that are in the case study portion of this project. | TI3: 1 | TQ3: 1 | TR3: 1 | TS3: 1 | TT3: 1 | TU3: 1 | TV3: 1 | XV3: 3 | YC3: 2 | YH3: 2 | YX3: 8 | ZN3: 0 | ZO3: 0 | ZU3: 1 | ZV3: 1 | ZW3: 4 | ZX3: 3 | ZY3: 2 | AAG3: 1 | AAH3: Provided feedback to guide research process | AAK3: 1 | AAL3: 1 | AAO3: 1 | AAP3: 1 | AAQ3: 2 | AAR3: 2 | AAS3: 2 | AAT3: 2 | AAU3: 2 | AAV3: 2 | AAY3: 4 | ABC3: Our evaluator provides essential on-going feedback on the research that is helpful for on-going improvement. | ABD3: 4 | ABH3: The evaluation feedback helped to summarize achievements and clarify future directions. | ABI3: Debra Bragg | ABJ3: bragg.associates.inc@gmail.com | ABK3: Bragg and Associates | ABL3: 2 | ABY3: 4 | ABZ3: 1 | ACA3: 1 | ACC3: Completing our analysis of our case study colleges and preparing a draft of our final report. | ACD3: 2 | ACF3: The role that community college technician programs can play in economic development can be better articulated by better understanding it through these case studies. By better articulating and showing examples, it may be more possible to measure when colleges are engaging in this approach. | ACG3: 2 | ACH3: 1 | ACR3: 3 | ADB3: 2 | ADZ3: 2 | AGQ3: 1 | AGR3: 1 | AGW3: 1 | AHG3: 4 | AHH3: 1 | AHI3: We have already submitted another proposal for an NSF-ATE project to expand on the work already done in the current grant. | AHN3: 1 | AHO3: =OR($YH3=1,$YC3=1,$XV3=1,$SC3=1,$RO3=1,$QE3=1,$PM3=1,$OV3=1,$OS3=1,$OG3=1,$ME3=1,$LT3=1,$LL3=1,$JQ3=1,$JP3=1,$JG3=1,$FI3=1,$BH3=1) -> TRUE | AHP3: =AND($YH3=2,$YC3=2,$XV3=2,$SC3=2,$RO3=2,$QE3=2,$PM3=2,$OV3=2,$OS3=2,$OG3=2,$ME3=2,$LT3=2,$LL3=2,$JQ3=2,$JP3=2,$JG3=2,$FI3=2,$BH3=2) -> FALSE | AHQ3: =AND($YH3=3,$YC3=3,$XV3=3,$SC3=3,$RO3=3,$QE3=3,$PM3=3,$OV3=3,$OS3=3,$OG3=3,$ME3=3,$LT3=3,$LL3=3,$JQ3=3,$JP3=3,$JG3=3,$FI3=3,$BH3=3) -> FALSE
A4: 1700678 | B4: SCME: Scaling Microsystems Support | C4: 4 | D4: 0 | E4: 2 | F4: 0 | G4: 1 | H4: 1 | J4: 1 | K4: 1 | T4: =COUNTIF(K4:S4,1) -> 1 | U4: www. scme-support.org | V4: 7 | W4: 2072345 | X4: 33 | AF4: 6 | AG4: 2 | AQ4: 2 | BA4: 2 | BB4: 6 | BD4: 6 | BE4: 1 | BG4: 5 | BH4: 3 | FI4: 3 | JG4: 2 | JP4: 1 | JQ4: 1 | KE4: 2 | KF4: 1 | KG4: 1 | KH4: 1 | KI4: 1 | KJ4: 1 | KK4: NanoHub | KL4: 1 | KM4: UNM Continuing Education | KN4: 1 | KO4: 1 | KP4: 1 | KQ4: 1 | KR4: 1 | KS4: 2 | KT4: 1 | KU4: 1 | KV4: 1 | KW4: 2 | KX4: 1 | LA4: 2 | LB4: 1 | LC4: 1 | LD4: 1 | LE4: 1 | LF4: 1 | LG4: NanoHub, MNT-EC | LH4: 1 | LI4: UNM Continuing Ed. | LJ4: 2 | LL4: 2 | LT4: 2 | ME4: 2 | OG4: 2 | OS4: 2 | OV4: 2 | PM4: 2 | PN4: 4 | QE4: 3 | RO4: 2 | SC4: 2 | XV4: 2 | YC4: 2 | YH4: 1 | YJ4: 1 | YK4: 1 | YL4: 1 | YM4: 1 | YN4: 1 | YQ4: 3 | YR4: 6 | YS4: 2 | YT4: 40 | YU4: 5 | YV4: 6 | YW4: 3 | YX4: 12 | YY4: 0 | YZ4: 1 | ZA4: 6 | ZE4: 1 | ZF4: 1 | ZG4: 1 | ZH4: 1 | ZI4: 3 | ZJ4: 2 | ZK4: 2 | ZL4: 1 | ZM4: 1 | ZN4: 0 | ZO4: 10000 | ZP4: 1 | ZQ4: 2 | ZU4: 1 | ZV4: 3 | ZW4: 3 | ZX4: 3 | ZY4: 2 | AAG4: 1 | AAH4: Last year of NCE, Not much was changed as we are sunsetting | AAL4: 1 | AAO4: 1 | AAP4: 2 | AAQ4: 2 | AAR4: 1 | AAS4: 1 | AAT4: 2 | AAU4: 2 | AAV4: 2 | AAX4: Other CC's | AAY4: 3 | ABB4: My evaluator has been with us for about a decade. We established a good working relationship and a standard system to collect and interpret data on usage. It is an efficient process. This last year, as it is a NCE, we only did some limited work (URE for students), discussion and mentoring of other CC's, etc. They have been good over the years to compile and present our work to NSF and our program officer. | ABD4: 3 | ABG4: Discussion on better surveys to get at the information required for our annual reports. Some adjustments to our methodologies were implemented over the years. Being informed as to other best practices from others, also, the evaluator was encouraged to share our best practices with others. | ABI4: Terryll Bailey | ABJ4: tbailey@theallisongroup.com | ABK4: the allison group | ABL4: 2 | ABY4: 4 | ABZ4: 1 | ACA4: 1 | ACC4: Bringing in the last 16 students to our University Cleanroom for hands-on experience in microfabrication and moving our curriculum to MNT-EC site and UNM's Continuing Education. UNM's Manufacturing Training and Technology Center will continue supporting the SCME website, online short course availability and dissemination. | ACD4: 2 | ACF4: How to run cleanroom hands-on experiences (shared with other university cleanrooms), how to organize and provide educational materials online, and perhaps, how to run virtual online student poster sessions. | ACG4: 2 | ACH4: 1 | ACR4: 3 | ADB4: 2 | AGQ4: 2 | AHH4: 5 | AHM4: We are a 4 year organization and ATE is not directly relevant to what we do. | AHN4: 1 | AHO4: =OR($YH4=1,$YC4=1,$XV4=1,$SC4=1,$RO4=1,$QE4=1,$PM4=1,$OV4=1,$OS4=1,$OG4=1,$ME4=1,$LT4=1,$LL4=1,$JQ4=1,$JP4=1,$JG4=1,$FI4=1,$BH4=1) -> TRUE | AHP4: =AND($YH4=2,$YC4=2,$XV4=2,$SC4=2,$RO4=2,$QE4=2,$PM4=2,$OV4=2,$OS4=2,$OG4=2,$ME4=2,$LT4=2,$LL4=2,$JQ4=2,$JP4=2,$JG4=2,$FI4=2,$BH4=2) -> FALSE | AHQ4: =AND($YH4=3,$YC4=3,$XV4=3,$SC4=3,$RO4=3,$QE4=3,$PM4=3,$OV4=3,$OS4=3,$OG4=3,$ME4=3,$LT4=3,$LL4=3,$JQ4=3,$JP4=3,$JG4=3,$FI4=3,$BH4=3) -> FALSE
A5: 1800909 | B5: Skills for Biomedical Emerging Technology Applications | C5: 1 | D5: 0 | E5: 2 | F5: 0 | G5: 2 | H5: 2 | J5: 3 | T5: =COUNTIF(K5:S5,1) -> 0 | U5: www.biotechworkforce.org | V5: 7 | W5: 995000 | X5: 15 | AF5: 3 | AG5: 2 | AQ5: 1 | AR5: 2 | AS5: 1 | AT5: 1 | AU5: 2 | AV5: 2 | AW5: 1 | AX5: 2 | AY5: 2 | AZ5: 2 | BA5: 2 | BB5: 6 | BD5: 6 | BE5: 1 | BG5: 6 | BH5: 2 | BI5: 1 | BO5: 2 | CU5: 4 | EV5: 1 | FF5: Complete the program of study and graduate to receive the AAS degree. | FI5: 2 | JG5: 2 | JP5: 2 | JQ5: 2 | LL5: 2 | LT5: 2 | ME5: 2 | OF5: Being able to directly participate in a business environment. | OG5: 2 | OS5: 2 | OV5: 2 | PM5: 2 | PN5: 1 | QA5: CompTIA A+, Linux+, Cloud+, VMWARE VCA & VCP, Red Hat RHCSA, Adanced Cloud Service Provider certs such as Cloud Engineer and Cloud Architect, Microsoft MDA certifications. | QB5: 1 | QC5: 3 | QE5: 1 | QG5: 1 | QI5: 7 | QT5: 12 | RA5: 2 | RB5: 5 | RF5: 1 | RK5: 1 | RL5: administrators knowledge | RM5: 2 | RO5: 2 | SC5: 2 | XV5: 2 | YC5: 1 | YD5: 2 | YH5: 1 | YJ5: 1 | YK5: 1 | YL5: 1 | YM5: 1 | YP5: mentoring | YQ5: 1 | YR5: 12 | YS5: 0 | YU5: 4 | YV5: 6 | YX5: 3 | YY5: 1 | YZ5: 2 | ZA5: 1 | ZB5: institutes | ZC5: 5 | ZE5: 1 | ZF5: 1 | ZG5: 1 | ZH5: 1 | ZI5: 1 | ZJ5: 1 | ZK5: 2 | ZL5: 1 | ZM5: 1 | ZN5: 500 | ZO5: 25000 | ZP5: 1 | ZR5: 1 | ZS5: visits to sites | ZT5: 2 | ZU5: 1 | ZV5: 1 | ZW5: 2 | ZX5: 3 | ZY5: 2 | AAD5: 1 | AAF5: 1 | AAJ5: 1 | AAK5: 1 | AAO5: 1 | AAP5: 1 | AAQ5: 1 | AAR5: 1 | AAS5: 1 | AAV5: 1 | AAX5: NC biotech center | AAY5: 4 | ABC5: Guides us | ABD5: 4 | ABH5: Helps us tailor our work to meet the needs of the participants and industry needs. | ABI5: Amy Germuth | ABJ5: agermuth@gmail.com | ABK5: Evalworks | ABL5: 2 | ABY5: 4 | ABZ5: 1 | ACA5: 1 | ACC5: Biosciences Administrator's Program and Biosciences Industry Fellows Program | ACD5: 1 | ACE5: Surveys- in person and follow up with telephone survey. | ACF5: Biosciences Administrator's Program, built with industry for CC administrators Biosciences Summer Industry Fellows Program built with industry for instructor PD. | ACG5: 2 | ACH5: 1 | ACR5: 3 | ADB5: 2 | ADZ5: 1 | AEA5: 1 | AEE5: 1 | AEG5: 1 | AEH5: Earning Certifications | AEI5: 2 | AEM5: 1 | AEO5: 1 | AES5: 1 | AET5: 1 | AFB5: 3 | AFC5: 2 | AFJ5: 1 | AFL5: 1 | AFN5: 1 | AGA5: 2 | AGC5: 2 | AGE5: 3 | AGN5: 2 | AGO5: 2 | AGP5: 82 | AGQ5: 2 | AHH5: 2 | AHJ5: The are additional areas uncovered from our grant that we would like to continue and address with another grant. | AHN5: 1 | AHO5: =OR($YH5=1,$YC5=1,$XV5=1,$SC5=1,$RO5=1,$QE5=1,$PM5=1,$OV5=1,$OS5=1,$OG5=1,$ME5=1,$LT5=1,$LL5=1,$JQ5=1,$JP5=1,$JG5=1,$FI5=1,$BH5=1) -> TRUE | AHP5: =AND($YH5=2,$YC5=2,$XV5=2,$SC5=2,$RO5=2,$QE5=2,$PM5=2,$OV5=2,$OS5=2,$OG5=2,$ME5=2,$LT5=2,$LL5=2,$JQ5=2,$JP5=2,$JG5=2,$FI5=2,$BH5=2) -> FALSE | AHQ5: =AND($YH5=3,$YC5=3,$XV5=3,$SC5=3,$RO5=3,$QE5=3,$PM5=3,$OV5=3,$OS5=3,$OG5=3,$ME5=3,$LT5=3,$LL5=3,$JQ5=3,$JP5=3,$JG5=3,$FI5=3,$BH5=3) -> FALSE
A6: 2400932 | B6: Enhancing Robotic Welding Education for Technicians | C6: 2 | D6: 0 | E6: 1 | F6: 2 | G6: 1 | H6: 2 | J6: 2 | T6: =COUNTIF(K6:S6,1) -> 0 | U6: https://ate.is/lplarocque | V6: 3 | W6: 446852 | X6: 4 | AF6: 1 | AG6: 1 | AH6: 7 | AP6: 1 | AQ6: 1 | AR6: 3 | AS6: 2 | AT6: 2 | AU6: 2 | AV6: 2 | AW6: 2 | AX6: 2 | AY6: 2 | AZ6: 2 | BA6: 2 | BB6: 6 | BD6: 6 | BE6: 1 | BG6: 3 | BH6: 3 | FI6: 3 | JG6: 2 | JP6: 3 | JQ6: 2 | LL6: 1 | LM6: 135605 | LN6: 1 | LP6: 0 | LQ6: 0 | LR6: 1 | LS6: It will help them gain hands on experience with industrial robotic welding. | LT6: 2 | ME6: 2 | OG6: 2 | OS6: 2 | OV6: 2 | PM6: 3 | PN6: 1 | QA6: Esri GIS Fundamentals Foundation Certificate | QB6: 1 | QC6: 2 | QE6: 3 | RO6: 3 | SC6: 2 | XV6: 3 | YC6: 3 | YH6: 3 | YV6: 3 | ZE6: 1 | ZF6: 2 | ZG6: 2 | ZH6: 2 | ZI6: 2 | ZJ6: 2 | ZK6: 2 | ZL6: 1 | ZM6: 1 | ZN6: 0 | ZO6: 0 | ZT6: 2 | ZU6: 1 | ZV6: 1 | ZW6: 2 | ZX6: 4 | AAO6: 4 | AAP6: 4 | AAQ6: 4 | AAR6: 4 | AAS6: 4 | AAT6: 4 | AAU6: 4 | AAV6: 4 | AAW6: 4 | AAY6: 3 | ABB6: The evaluator is encouraging and informative. | ABD6: 1 | ABE6: We haven’t had an evaluation yet. Still in process. | ABI6: Kurt Steuck | ABJ6: Kurt.Steuck@steuckassoc.com | ABK6: Steuck & Associates LLC | ABL6: 2 | ABY6: 1 | ABZ6: 2 | ACA6: 1 | ACC6: Purchasing equipment | ACD6: 2 | ACF6: N/A | ACG6: 2 | ACH6: 1 | ACL6: 1 | ACM6: 1 | ACP6: 1 | ACQ6: Personally, I cannot wear ERT, so not sure how I would create assignments | ACR6: 2 | ACV6: 2 | ACW6: 2 | ACZ6: 3 | ADB6: 2 | AGQ6: 1 | AGS6: 1 | AHE6: GeoTech Center | AHG6: 1 | AHH6: 2 | AHJ6: Even though we are in year 1 of the project, the NSF ATE grant has provided us with a framework and monetary means to enhance our program and make connections and relationships with people we might not have otherwise. | AHN6: 1 | AHO6: =OR($YH6=1,$YC6=1,$XV6=1,$SC6=1,$RO6=1,$QE6=1,$PM6=1,$OV6=1,$OS6=1,$OG6=1,$ME6=1,$LT6=1,$LL6=1,$JQ6=1,$JP6=1,$JG6=1,$FI6=1,$BH6=1) -> TRUE | AHP6: =AND($YH6=2,$YC6=2,$XV6=2,$SC6=2,$RO6=2,$QE6=2,$PM6=2,$OV6=2,$OS6=2,$OG6=2,$ME6=2,$LT6=2,$LL6=2,$JQ6=2,$JP6=2,$JG6=2,$FI6=2,$BH6=2) -> FALSE | AHQ6: =AND($YH6=3,$YC6=3,$XV6=3,$SC6=3,$RO6=3,$QE6=3,$PM6=3,$OV6=3,$OS6=3,$OG6=3,$ME6=3,$LT6=3,$LL6=3,$JQ6=3,$JP6=3,$JG6=3,$FI6=3,$BH6=3) -> FALSE
A7: 2300744 | B7: Creating Advanced Manufacturing Pathways Program | C7: 2 | D7: 0 | E7: 1 | F7: 2 | G7: 1 | H7: 2 | J7: 2 | T7: =COUNTIF(K7:S7,1) -> 0 | U7: None | V7: 3 | W7: 347969 | X7: 19 | AF7: 4 | AG7: 1 | AH7: 7 | AP7: 1 | AQ7: 1 | AR7: 2 | AS7: 2 | AT7: 2 | AU7: 2 | AV7: 2 | AW7: 2 | AX7: 2 | AY7: 2 | AZ7: 2 | BA7: 2 | BB7: 6 | BD7: 6 | BE7: 1 | BG7: 4 | BH7: 2 | CD7: 9 | CE7: 4 | CJ7: 2 | CK7: 2 | CO7: 5 | CQ7: 9 | CW7: 1 | CX7: 1 | DB7: 2 | DD7: 4 | FA7: 9 | FB7: 4 | FG7: 0 | FH7: 0 | FI7: 2 | JG7: 2 | JP7: 2 | JQ7: 1 | KN7: 2 | KO7: 2 | KP7: 1 | KQ7: 1 | KR7: 2 | KS7: 2 | KT7: 2 | KU7: 2 | KV7: 2 | KW7: 2 | KX7: 2 | KY7: 2 | LA7: 2 | LB7: 2 | LC7: 1 | LD7: 2 | LE7: 2 | LF7: 2 | LH7: 2 | LJ7: 2 | LL7: 3 | LT7: 2 | ME7: 1 | MF7: 2 | MG7: 2 | MH7: 1 | MI7: 2 | MJ7: 2 | MK7: 2 | ML7: 2 | MN7: 1 | MP7: 16 | MV7: 32 | NB7: 2 | NH7: 1 | NN7: 2 | NT7: 1 | OA7: 13 | OG7: 2 | OS7: 2 | OV7: 2 | PM7: 2 | PN7: 4 | QE7: 2 | RO7: 2 | SC7: 2 | XV7: 2 | YC7: 2 | YH7: 2 | YV7: 8 | YW7: 2 | YX7: 0 | YY7: 2 | YZ7: 1 | ZA7: 1 | ZE7: 1 | ZF7: 1 | ZG7: 2 | ZH7: 2 | ZI7: 1 | ZJ7: 3 | ZK7: 2 | ZL7: 1 | ZM7: 1 | ZN7: 0 | ZO7: 0 | ZU7: 1 | ZV7: 1 | ZW7: 3 | ZX7: 3 | ZY7: 2 | AAF7: 1 | AAI7: 1 | AAJ7: 1 | AAO7: 1 | AAP7: 1 | AAQ7: 1 | AAR7: 1 | AAS7: 2 | AAT7: 2 | AAU7: 2 | AAV7: 3 | AAW7: 4 | AAY7: 3 | ABB7: Our evaluators have been helpful with designing and implementing surveys. They have also been instrumental in compiling the results. | ABD7: 3 | ABG7: Seeing the results of the various surveys has help guide us to make changes in our strategies for outreach. | ABI7: Christy Brinkley | ABJ7: cbrinkley@astate.edu | ABK7: Arkansas State University | ABL7: 1 | ABM7: Sheila Stowers | ABN7: sstowers@astate.edu | ABO7: Arkansas State University | ABY7: 2 | ABZ7: 2 | ACA7: 2 | ACC7: The creation of apprenticeships. | ACD7: 1 | ACE7: Demographic, wage, educational, and satisfaction data was assessed via a survey | ACF7: The most promising practice has been using apprenticeships to start a dialog with local industry. It has been a great way to get conversation started and get them engaged. | ACG7: 2 | ACH7: 1 | ACR7: 1 | ADB7: 2 | ADZ7: 1 | AEE7: 1 | AEF7: 1 | AEG7: 1 | AEH7: Two-year mentoring initiative | AEM7: 1 | AEN7: 2 | AEO7: 1 | AER7: 1 | AFA7: 3 | AFG7: 1 | AFI7: 1 | AFJ7: 1 | AFO7: 1 | AFP7: 1 | AFS7: 1 | AFX7: 3 | AFZ7: 3 | AGA7: 3 | AGF7: 4 | AGG7: 4 | AGJ7: 4 | AGN7: 2 | AGO7: 2 | AGP7: 88 | AGQ7: 2 | AHH7: 1 | AHI7: AACC has a long history and partnership with the National Science Foundation to manage the annual ATE Confernece, run the MentorLinks program, and to provide dissemination, networking, and leadership development opportunities to the nation's community colleges. We seek to continue that work beyond the scope of our current award. | AHN7: 1 | AHO7: =OR($YH7=1,$YC7=1,$XV7=1,$SC7=1,$RO7=1,$QE7=1,$PM7=1,$OV7=1,$OS7=1,$OG7=1,$ME7=1,$LT7=1,$LL7=1,$JQ7=1,$JP7=1,$JG7=1,$FI7=1,$BH7=1) -> TRUE | AHP7: =AND($YH7=2,$YC7=2,$XV7=2,$SC7=2,$RO7=2,$QE7=2,$PM7=2,$OV7=2,$OS7=2,$OG7=2,$ME7=2,$LT7=2,$LL7=2,$JQ7=2,$JP7=2,$JG7=2,$FI7=2,$BH7=2) -> FALSE | AHQ7: =AND($YH7=3,$YC7=3,$XV7=3,$SC7=3,$RO7=3,$QE7=3,$PM7=3,$OV7=3,$OS7=3,$OG7=3,$ME7=3,$LT7=3,$LL7=3,$JQ7=3,$JP7=3,$JG7=3,$FI7=3,$BH7=3) -> FALSE
A8: 2300388 | B8: An Automation Robotics Program for Nontraditional Students | C8: 3 | D8: 0 | E8: 2 | F8: 0 | G8: 1 | H8: 2 | J8: 2 | T8: =COUNTIF(K8:S8,1) -> 0 | U8: https://ate.community/jthorstad | V8: 3 | W8: 350000 | X8: 20 | AF8: 4 | AG8: 1 | AH8: 7 | AP8: 1 | AQ8: 2 | BA8: 2 | BB8: 6 | BD8: 6 | BE8: 1 | BG8: 4 | BH8: 1 | CD8: 264 | CE8: 264 | CI8: 0 | CJ8: 11 | CK8: 2 | CL8: 1 | CM8: 3 | CN8: 0 | CO8: 10 | CP8: 3 | CQ8: 23 | CR8: 5 | CV8: 1 | CW8: 30 | CX8: 31 | CY8: 8 | CZ8: 19 | DA8: 0 | DB8: 87 | DC8: 19 | DD8: 167 | DE8: 12 | FA8: 0 | FB8: 0 | FC8: 0 | FD8: 0 | FG8: 2 | FH8: 159 | FI8: 1 | FJ8: 5 | HT8: 14 | HV8: 58 | JG8: 2 | JP8: 2 | JQ8: 2 | LL8: 1 | LM8: 155572.71 | LN8: 1 | LP8: 10 | LQ8: 75 | LR8: 5 | LS8: Through the purchase of this equipment, we were able to begin offering our program at the Brooklyn Park campus of our college. This allowed us to start duplicating the program at our north campus where demand for the program is high. | LT8: 2 | ME8: 1 | MF8: 1 | MG8: 2 | MH8: 1 | MI8: 2 | MJ8: 1 | MK8: 2 | MN8: 1 | MP8: 40 | MR8: 20 | MV8: 52 | MX8: 16 | NB8: 2 | ND8: 2 | NH8: 1 | NJ8: 1 | NN8: 2 | NP8: 1 | NT8: 2 | NV8: 2 | NY8: 88 | OA8: 24 | OC8: 9 | OG8: 2 | OS8: 2 | OV8: 2 | PM8: 1 | PN8: 2 | PO8: 1 | PP8: 1 | PQ8: 2 | PR8: 2 | PS8: 1 | PV8: 2 | PW8: 1 | PX8: 2 | QE8: 1 | QF8: 0 | QG8: 1 | QH8: 0 | QI8: 0 | QP8: 0 | QQ8: 5 | QR8: 6 | QS8: 0 | RE8: 1 | RF8: 1 | RG8: 2 | RH8: 1 | RI8: 2 | RJ8: 2 | RM8: 2 | RO8: 2 | SC8: 2 | XV8: 2 | YC8: 2 | YH8: 2 | YV8: 10 | YW8: 1 | ZE8: 1 | ZF8: 1 | ZG8: 2 | ZH8: 2 | ZI8: 1 | ZJ8: 1 | ZK8: 2 | ZL8: 1 | ZM8: 1 | ZN8: 33027.52 | ZO8: 541976.25 | ZP8: 2 | ZQ8: 1 | ZU8: 1 | ZV8: 1 | ZW8: 2 | ZX8: 3 | AAK8: 1 | AAO8: 1 | AAP8: 1 | AAQ8: 1 | AAR8: 1 | AAS8: 2 | AAT8: 2 | AAU8: 2 | AAV8: 2 | AAY8: 2 | ABA8: We are new to ATE/NSF. We are slowly learning what our evaluator can do to help us and what role that person plays in our process. We are working on plans to take better advantage of this role in future activities. | ABD8: 2 | ABF8: Once again, based on our being new to this process, we are learning about this role and how to better capitalize on it in the future. | ABI8: William Campbell | ABJ8: wm.e.campbell@uwrf.edu | ABK8: Campbell Grants & Research | ABL8: 2 | ABY8: 2 | ABZ8: 2 | ACA8: 1 | ACC8: Our most important achievement was the offering of program courses at our Brooklyn Park campus. | ACD8: 1 | ACE8: Basic information regarding the number of courses offered and number of students impacted. | ACF8: 1) Working with industry is vital, but requires patience. Industry support is key to any program expansion. | ACG8: 2 | ACI8: 1 | ACM8: 1 | ACS8: 2 | ACW8: 2 | ADB8: 2 | ADZ8: 1 | AEC8: 1 | AEF8: 1 | AEK8: 2 | AEN8: 2 | AFH8: 1 | AFJ8: 1 | AFK8: 1 | AFY8: 2 | AGA8: 2 | AGB8: 2 | AGN8: 3 | AGO8: 3 | AGP8: 50 | AGQ8: 2 | AHH8: 2 | AHJ8: I hope the college continues going after ATE projects to improve the technical courses | AHN8: 1 | AHO8: =OR($YH8=1,$YC8=1,$XV8=1,$SC8=1,$RO8=1,$QE8=1,$PM8=1,$OV8=1,$OS8=1,$OG8=1,$ME8=1,$LT8=1,$LL8=1,$JQ8=1,$JP8=1,$JG8=1,$FI8=1,$BH8=1) -> TRUE | AHP8: =AND($YH8=2,$YC8=2,$XV8=2,$SC8=2,$RO8=2,$QE8=2,$PM8=2,$OV8=2,$OS8=2,$OG8=2,$ME8=2,$LT8=2,$LL8=2,$JQ8=2,$JP8=2,$JG8=2,$FI8=2,$BH8=2) -> FALSE | AHQ8: =AND($YH8=3,$YC8=3,$XV8=3,$SC8=3,$RO8=3,$QE8=3,$PM8=3,$OV8=3,$OS8=3,$OG8=3,$ME8=3,$LT8=3,$LL8=3,$JQ8=3,$JP8=3,$JG8=3,$FI8=3,$BH8=3) -> FALSE
A9: 2348815 | B9: Agricultural Robotics and Automation Technologies | C9: 1 | D9: 0 | E9: 1 | F9: 2 | G9: 1 | H9: 2 | J9: 2 | T9: =COUNTIF(K9:S9,1) -> 0 | U9: https://www.agcentric.org/education-training/agcentric-case-nsf/ | V9: 3 | W9: 648668 | X9: 7 | AF9: 1 | AG9: 1 | AH9: 7 | AJ9: Robotics & Automation | AP9: 1 | AQ9: 1 | AR9: 5 | AS9: 1 | AT9: 1 | AU9: 3 | AV9: 1 | AW9: 1 | AX9: 1 | AY9: 1 | AZ9: 3 | BA9: 2 | BB9: 6 | BD9: 6 | BE9: 1 | BG9: 4 | BH9: 3 | BI9: 1 | BO9: 2 | CU9: 0 | EV9: 1 | FF9: completed all the required and elective courses in the program | FI9: 1 | FJ9: 2 | HS9: 0 | HT9: 0 | HU9: 0 | HV9: 0 | HW9: 0 | JG9: 3 | JP9: 1 | JQ9: 2 | JR9: 2 | JS9: 4 | JT9: 2 | JU9: 2 | JV9: 2 | JW9: 2 | JX9: 0 | JY9: 2 | JZ9: 2 | KA9: 0 | KB9: 0 | KD9: 0 | KE9: 1 | KF9: 1 | KG9: 1 | KH9: 1 | KI9: 1 | KJ9: 2 | KL9: 2 | LJ9: 2 | LL9: 3 | LT9: 3 | ME9: 2 | OG9: 2 | OS9: 2 | OV9: 2 | PM9: 3 | PN9: 3 | QE9: 3 | RO9: 1 | RP9: 2 | RR9: 1 | RS9: Curriculum Development Retreat | RX9: 23 | SC9: 2 | XV9: 2 | YC9: 3 | YH9: 3 | YV9: 7 | YW9: 3 | YX9: 3 | YY9: 7 | YZ9: 0 | ZA9: 0 | ZB9: CASE | ZC9: 3 | ZE9: 1 | ZF9: 1 | ZG9: 2 | ZH9: 2 | ZI9: 1 | ZJ9: 3 | ZK9: 2 | ZL9: 3 | ZM9: 1 | ZN9: 0 | ZO9: 0 | ZT9: 2 | ZU9: 1 | ZV9: 1 | ZW9: 3 | ZX9: 2 | ZY9: 2 | AAB9: 1 | AAJ9: 1 | AAO9: 4 | AAP9: 1 | AAQ9: 2 | AAR9: 1 | AAS9: 1 | AAT9: 4 | AAU9: 4 | AAV9: 2 | AAY9: 4 | ABC9: They continue to engage with our monthly meetings, curriculum development team, and offer guidance continually as well offer encouragement and support. | ABD9: 3 | ABG9: They continue to offer evaluative items for our work going forward, so we plan evaluation into all our activities that is meaningful. | ABI9: Sandra Mikolaski | ABJ9: smikolaski@gmail.com | ABK9: External Evaluator | ABL9: 1 | ABM9: Manjari Wijenaike | ABN9: manjari.wijenaike@gmail.com | ABO9: External Evaluator | ABY9: 4 | ABZ9: 1 | ACA9: 1 | ACC9: Get an advisory/curriculum team assembled and develop curriculum for training. | ACD9: 2 | ACF9: Connection with secondary, post-secondary, and industry to develop new pathways supported by relevant curriculum that is consistent to all three partners. | ACG9: 1 | ADG9: 1 | ADN9: 1 | ADU9: 1 | ADX9: 1 | ADY9: 2 | ADZ9: 1 | AEC9: 1 | AEK9: 2 | AEU9: 1 | AFD9: 2 | AFH9: 1 | AFJ9: 1 | AFL9: 1 | AFY9: 2 | AGA9: 2 | AGC9: 2 | AGN9: 2 | AGO9: 2 | AGP9: 70 | AGQ9: 2 | AHH9: 5 | AHN9: 2 | AHO9: =OR($YH9=1,$YC9=1,$XV9=1,$SC9=1,$RO9=1,$QE9=1,$PM9=1,$OV9=1,$OS9=1,$OG9=1,$ME9=1,$LT9=1,$LL9=1,$JQ9=1,$JP9=1,$JG9=1,$FI9=1,$BH9=1) -> TRUE | AHP9: =AND($YH9=2,$YC9=2,$XV9=2,$SC9=2,$RO9=2,$QE9=2,$PM9=2,$OV9=2,$OS9=2,$OG9=2,$ME9=2,$LT9=2,$LL9=2,$JQ9=2,$JP9=2,$JG9=2,$FI9=2,$BH9=2) -> FALSE | AHQ9: =AND($YH9=3,$YC9=3,$XV9=3,$SC9=3,$RO9=3,$QE9=3,$PM9=3,$OV9=3,$OS9=3,$OG9=3,$ME9=3,$LT9=3,$LL9=3,$JQ9=3,$JP9=3,$JG9=3,$FI9=3,$BH9=3) -> FALSE
A10: 2400736 | B10: Advancing Career and Technical Skills: Through the science of material, nondestructive testing and welding education. | C10: 2 | D10: 0 | E10: 1 | F10: 2 | G10: 1 | H10: 2 | J10: 1 | K10: 1 | T10: =COUNTIF(K10:S10,1) -> 1 | U10: NA | V10: 3 | W10: 331290 | X10: 4 | AF10: 1 | AG10: 1 | AH10: 9 | AI10: NDT | AP10: 1 | AQ10: 2 | BA10: 2 | BB10: 7 | BC10: Bohemian | BD10: 7 | BE10: 1 | BG10: 4 | BH10: 3 | FI10: 1 | FJ10: 1 | HT10: 9 | JG10: 2 | JP10: 1 | JQ10: 2 | JR10: 1 | JT10: 1 | JU10: 1 | JX10: 5 | JY10: 5 | JZ10: 5 | KA10: 3 | KB10: 12 | KE10: 2 | KF10: 2 | KG10: 1 | LJ10: 2 | LL10: 3 | LT10: 2 | ME10: 1 | MF10: 1 | MK10: 2 | NY10: 18 | OG10: 3 | OS10: 2 | OV10: 2 | PM10: 1 | PN10: 2 | PQ10: 1 | PS10: 1 | PW10: 1 | QE10: 3 | RO10: 1 | RP10: 2 | RR10: 3 | RS10: PCC Welding Advisory Committee | RT10: AWS Executive Committee Dist. 20 | RU10: ASNT Southern Colorado Section | RX10: 25 | RY10: 23 | RZ10: 17 | SC10: 3 | XV10: 2 | YC10: 2 | YH10: 2 | YV10: 10 | YX10: 4 | YY10: 6 | ZE10: 1 | ZF10: 1 | ZG10: 3 | ZH10: 3 | ZI10: 1 | ZJ10: 2 | ZK10: 2 | ZL10: 3 | ZM10: 1 | ZO10: 4000 | ZR10: 1 | ZS10: Material/Consumables | ZU10: 1 | ZV10: 1 | ZW10: 3 | ZX10: 3 | AAO10: 1 | AAP10: 1 | AAQ10: 1 | AAR10: 1 | AAS10: 1 | AAT10: 1 | AAU10: 1 | AAV10: 1 | AAY10: 3 | ABB10: Because they are wonderful and have years of valuable experience. | ABD10: 3 | ABG10: They have valuable experience with NSF projects. | ABI10: Tim and Sally Griffin | ABJ10: timgriffinatconifer@gmail.com | ABK10: The Conifer Group | ABY10: 1 | ABZ10: 2 | ACA10: 1 | ACC10: Development of the first NDT class in the CCCS. | ACD10: 1 | ACE10: Issued NDT qualification hours to students. | ACF10: Developed first NDT class in CCCS. | ACG10: 2 | ACH10: 1 | ACR10: 1 | ADB10: 2 | AGQ10: 2 | AHH10: 1 | AHI10: Expansion and continuation of the CCPI-STEM project. | AHN10: 1 | AHO10: =OR($YH10=1,$YC10=1,$XV10=1,$SC10=1,$RO10=1,$QE10=1,$PM10=1,$OV10=1,$OS10=1,$OG10=1,$ME10=1,$LT10=1,$LL10=1,$JQ10=1,$JP10=1,$JG10=1,$FI10=1,$BH10=1) -> TRUE | AHP10: =AND($YH10=2,$YC10=2,$XV10=2,$SC10=2,$RO10=2,$QE10=2,$PM10=2,$OV10=2,$OS10=2,$OG10=2,$ME10=2,$LT10=2,$LL10=2,$JQ10=2,$JP10=2,$JG10=2,$FI10=2,$BH10=2) -> FALSE | AHQ10: =AND($YH10=3,$YC10=3,$XV10=3,$SC10=3,$RO10=3,$QE10=3,$PM10=3,$OV10=3,$OS10=3,$OG10=3,$ME10=3,$LT10=3,$LL10=3,$JQ10=3,$JP10=3,$JG10=3,$FI10=3,$BH10=3) -> FALSE
A11: 1836721 | B11: AccessATE: Making Community College Technician Education More Accessible for Everyone | C11: 1 | D11: 0 | E11: 2 | F11: 0 | G11: 1 | H11: 1 | J11: 2 | T11: =COUNTIF(K11:S11,1) -> 0 | U11: accessate.net | V11: 4 | W11: 2520374 | X11: 39 | AE11: Accessibility | AF11: 8 | AG11: 2 | AQ11: 1 | AR11: 3 | AS11: 1 | AT11: 1 | AU11: 1 | AV11: 1 | AW11: 1 | AX11: 1 | AY11: 1 | AZ11: 2 | BA11: 2 | BB11: 6 | BD11: 6 | BE11: 2 | BG11: 5 | BH11: 2 | FI11: 2 | JG11: 2 | JP11: 2 | JQ11: 2 | LL11: 2 | LT11: 2 | ME11: 2 | OG11: 2 | OS11: 2 | OV11: 2 | PM11: 2 | PN11: 2 | QE11: 2 | RO11: 2 | SC11: 2 | XV11: 2 | YC11: 2 | YH11: 1 | YJ11: 1 | YK11: 2 | YL11: 1 | YM11: 1 | YN11: 2 | YO11: 2 | YS11: 2 | YT11: 17 | YU11: 20 | YV11: 0 | YW11: 0 | YX11: 0 | YY11: 0 | YZ11: 0 | ZA11: 0 | ZC11: 0 | ZN11: 0 | ZO11: 0 | ZU11: 1 | ZV11: 1 | ZW11: 4 | ZX11: 3 | AAO11: 1 | AAP11: 2 | AAQ11: 2 | AAR11: 2 | AAS11: 1 | AAT11: 2 | AAU11: 2 | AAV11: 2 | AAW11: 2 | AAY11: 4 | ABC11: Our evaluators help us understand the impact of our work on the ATE community and help us consider what will make the work more effective. | ABD11: 4 | ABH11: The findings helped steer the work of our project; we are in the final year and in an NCE also. | ABI11: Kathleen Dean | ABJ11: kdean@therucksgroup.com | ABK11: The Rucks Group | ABL11: 1 | ABM11: Alyssa Hokky | ABN11: ahokky@therucksgroup.com | ABO11: The Rucks Group | ABY11: 4 | ABZ11: 1 | ACA11: 1 | ACC11: A new set of case studies developed and released in collaboration with our partners at CAST - also our booth at the HI-TEC conference. | ACD11: 2 | ACF11: Consider accessibility from the beginning of your project; it's much easier to build it in than go back and make changes. | ACG11: 2 | ACH11: 1 | ACR11: 3 | ADB11: 2 | ADZ11: 1 | AEE11: 1 | AEG11: 1 | AEH11: Monthly online check-ins + 1.5 day in-person meeting | AEM11: 1 | AEO11: 1 | AEP11: 1 | AEV11: 1 | AEY11: 3 | AFE11: 1 | AFI11: 1 | AFJ11: 1 | AFL11: 1 | AFM11: 1 | AFP11: 1 | AFZ11: 4 | AGA11: 1 | AGC11: 1 | AGD11: 3 | AGG11: 4 | AGN11: 3 | AGO11: 3 | AGP11: 100 | AGQ11: 2 | AHH11: 2 | AHJ11: We would like to expand our professional development to other writers as well as modify our professional development to education the next generation of reviewers. | AHN11: 1 | AHO11: =OR($YH11=1,$YC11=1,$XV11=1,$SC11=1,$RO11=1,$QE11=1,$PM11=1,$OV11=1,$OS11=1,$OG11=1,$ME11=1,$LT11=1,$LL11=1,$JQ11=1,$JP11=1,$JG11=1,$FI11=1,$BH11=1) -> TRUE | AHP11: =AND($YH11=2,$YC11=2,$XV11=2,$SC11=2,$RO11=2,$QE11=2,$PM11=2,$OV11=2,$OS11=2,$OG11=2,$ME11=2,$LT11=2,$LL11=2,$JQ11=2,$JP11=2,$JG11=2,$FI11=2,$BH11=2) -> FALSE | AHQ11: =AND($YH11=3,$YC11=3,$XV11=3,$SC11=3,$RO11=3,$QE11=3,$PM11=3,$OV11=3,$OS11=3,$OG11=3,$ME11=3,$LT11=3,$LL11=3,$JQ11=3,$JP11=3,$JG11=3,$FI11=3,$BH11=3) -> FALSE
A12: 2400426 | B12: ETSTE DCL: Developing and Using Resources and Strategies to Educate Technicians in Vacuum Technologies | C12: 1 | D12: 0 | E12: 1 | F12: 1 | G12: 1 | H12: 2 | J12: 2 | T12: =COUNTIF(K12:S12,1) -> 0 | U12: http://ate.is/vacuum-tech-education | V12: 3 | W12: 649647 | X12: 33 | AF12: 6 | AG12: 1 | AH12: 9 | AI12: Vacuum Technology | AP12: 1 | AQ12: 1 | AR12: 3 | AS12: 1 | AT12: 1 | AU12: 1 | AV12: 1 | AW12: 1 | AX12: 1 | AY12: 1 | AZ12: 1 | BA12: 2 | BB12: 6 | BD12: 6 | BE12: 2 | BG12: 4 | BH12: 2 | FI12: 2 | JG12: 2 | JP12: 3 | JQ12: 2 | LL12: 3 | LT12: 2 | ME12: 2 | OF12: Workplace-based learning opportunities gave NCAT students the opportunity to apply in-classroom concepts to real-world applications. This experience assisted in students understanding the business processes related to Autonomous Technology. For example, the students learned flight planning techniques, implemented autonomous flight plans, and interpreted the data to create value for the work environment. | OG12: 2 | OS12: 2 | OV12: 2 | PM12: 2 | PN12: 1 | QA12: Federal Aviation Administration Remote Pilot Certificate AUVSI Trusted Operator EV Pro+ Level 1 Federal Aviation Administration TRUST Certificate | QB12: 1 | QC12: 1 | QD12: sUAS industry - FAA Commercial UAS Certificate, Trusted Operator Program, FAA TRUST Certificate Automotive - EV Pro+ Large UAS/Aviation industry - ASTM Aircraft Electronic Technician Certificate, radio communication endorsement, dependent navigation endorsement, autonomous navigation endorsement, Federal Communication Commission General Radiotelephone Operator License, COMPTIA aero IT | QE12: 3 | RO12: 2 | SC12: 2 | XV12: 3 | YC12: 2 | YH12: 2 | YV12: 0 | YW12: 0 | YX12: 0 | YY12: 0 | YZ12: 0 | ZA12: 1 | ZC12: 0 | ZN12: 0 | ZO12: 0 | ZT12: 4 | ZU12: 1 | ZV12: 1 | ZW12: 4 | ZX12: 4 | AAO12: 2 | AAP12: 4 | AAQ12: 4 | AAR12: 4 | AAS12: 2 | AAT12: 4 | AAU12: 4 | AAV12: 4 | AAW12: 4 | AAY12: 4 | ABC12: Our external evaluator participates in team meetings and in all planning activities for project activities, for example, workshops. Having the external evaluator to participate in projects :hands-on" allows us effectively plan for capturing correct feedback information and modify activities to reflect the previous feedback. | ABD12: 3 | ABG12: This particular project had just started in Fall of 2024, so we only had couple of month of work under the belt. Even so, our external evaluator was able to utilize evaluation results from previous project in the current project as we were gearing up for several of the planned activities. | ABI12: Bob Bailey | ABJ12: bobbailey@outcomesconsultingservices.com | ABK12: Outcomes Consulting Services | ABL12: 2 | ABY12: 1 | ABZ12: 1 | ACA12: 1 | ACC12: The project has just started at the end of 2024. The major achievement was confirming the project team and kicking off the project plan. | ACD12: 2 | ACF12: Reaching out to industry and subject matter experts early in the project for the formative feedback. | ACG12: 1 | ADE12: 1 | ADF12: 1 | ADG12: 1 | ADL12: 2 | ADM12: 4 | ADN12: 4 | ADP12: 1 | ADT12: 1 | ADX12: 1 | ADY12: 1 | ADZ12: 1 | AEA12: 1 | AEB12: 1 | AEC12: 1 | AEE12: 1 | AEF12: 1 | AEI12: 1 | AEJ12: 2 | AEK12: 2 | AEM12: 3 | AEN12: 3 | AFG12: 1 | AFH12: 1 | AFI12: 1 | AFK12: 1 | AFL12: 1 | AFM12: 1 | AFN12: 1 | AFO12: 1 | AFP12: 1 | AFR12: 1 | AFS12: 1 | AFX12: 3 | AFY12: 4 | AFZ12: 2 | AGB12: 1 | AGC12: 1 | AGD12: 2 | AGE12: 3 | AGF12: 4 | AGG12: 4 | AGI12: 4 | AGJ12: 5 | AGN12: 2 | AGO12: 2 | AGP12: 51 | AGQ12: 1 | AGR12: 1 | AGS12: 1 | AGT12: 1 | AGW12: 1 | AGX12: 1 | AGY12: 1 | AHA12: 1 | AHG12: 4 | AHH12: 1 | AHN12: 1 | AHO12: =OR($YH12=1,$YC12=1,$XV12=1,$SC12=1,$RO12=1,$QE12=1,$PM12=1,$OV12=1,$OS12=1,$OG12=1,$ME12=1,$LT12=1,$LL12=1,$JQ12=1,$JP12=1,$JG12=1,$FI12=1,$BH12=1) -> FALSE | AHP12: =AND($YH12=2,$YC12=2,$XV12=2,$SC12=2,$RO12=2,$QE12=2,$PM12=2,$OV12=2,$OS12=2,$OG12=2,$ME12=2,$LT12=2,$LL12=2,$JQ12=2,$JP12=2,$JG12=2,$FI12=2,$BH12=2) -> FALSE | AHQ12: =AND($YH12=3,$YC12=3,$XV12=3,$SC12=3,$RO12=3,$QE12=3,$PM12=3,$OV12=3,$OS12=3,$OG12=3,$ME12=3,$LT12=3,$LL12=3,$JQ12=3,$JP12=3,$JG12=3,$FI12=3,$BH12=3) -> FALSE
A13: 1931215 | B13: Engaging Educators, Strengthening Practice: Creating & Sustaining Successful Industry-Education Partnerships | C13: 1 | D13: 0 | E13: 2 | F13: 0 | G13: 1 | H13: 2 | J13: 2 | T13: =COUNTIF(K13:S13,1) -> 0 | U13: https://workingpartnersproject.org | V13: 4 | W13: 1970027 | X13: 38 | AD13: Education-Industry Partnerships | AF13: 7 | AG13: 2 | AQ13: 1 | AR13: 3 | AS13: 1 | AT13: 1 | AU13: 1 | AV13: 1 | AW13: 1 | AX13: 1 | BA13: 2 | BB13: 6 | BD13: 6 | BE13: 2 | BG13: 5 | BH13: 2 | FI13: 2 | JG13: 2 | JP13: 2 | JQ13: 2 | LL13: 2 | LT13: 2 | ME13: 2 | OF13: Opportunity to explore teaching career and to apply what they learn. | OG13: 2 | OS13: 2 | OV13: 2 | PM13: 2 | PN13: 1 | QA13: Microsoft Certified Educator (MCE) | QB13: 1 | QC13: 3 | QE13: 2 | RO13: 1 | RP13: 2 | RR13: 2 | RS13: Workshop Alumni Preconference workshop - HI-TEC | RT13: Preconference workshop - ATE PI | RX13: 52 | RY13: 40 | SC13: 2 | XV13: 1 | XW13: 1 | YC13: 2 | YH13: 1 | YJ13: 1 | YK13: 1 | YL13: 1 | YM13: 1 | YQ13: 4 | YR13: 40 | YS13: 1 | YT13: 30 | YU13: 25 | YV13: 12 | YW13: 2 | YX13: 90 | YY13: 20 | ZA13: 5 | ZE13: 1 | ZF13: 2 | ZG13: 2 | ZH13: 2 | ZI13: 2 | ZJ13: 2 | ZK13: 2 | ZL13: 2 | ZM13: 2 | ZN13: 0 | ZO13: 0 | ZT13: 4 | ZU13: 1 | ZV13: 3 | ZW13: 3 | ZX13: 3 | ZY13: 2 | AAB13: 1 | AAK13: 1 | AAO13: 1 | AAP13: 2 | AAQ13: 2 | AAR13: 2 | AAS13: 1 | AAT13: 2 | AAU13: 2 | AAV13: 2 | AAY13: 3 | ABB13: Quick, thoughtful responses to our questions. Well-crafted reports. | ABD13: 2 | ABF13: We have our ear to the ground pretty closely so the reports from the external evaluator provided confirmation but not a lot of new information. | ABI13: Kristi Manseth | ABJ13: Kristi@pacific-research.org | ABK13: Pacific Research & Evaluation | ABL13: 1 | ABM13: Regina Wheeler | ABN13: Regina@pacific-research.org | ABO13: Pacific Research & Evaluation | ABY13: 4 | ABZ13: 2 | ACA13: 1 | ACC13: Workshops continued to attract increasing numbers of applicants who report great satisfaction and learning post-workshop. | ACD13: 1 | ACE13: Pre/Post-Workshop confidence levels around industry partnerships; knowledge gains. | ACF13: Provide timely and personal feedback to professional development workshop participants as much as is possible. Let peers work together to find solutions to common issues. | ACG13: 1 | ADC13: 1 | ADD13: 1 | ADE13: 1 | ADF13: 1 | ADG13: 1 | ADJ13: 4 | ADK13: 4 | ADL13: 4 | ADM13: 4 | ADN13: 4 | ADT13: 1 | ADU13: 1 | ADV13: 1 | ADW13: Head-mount, laptop, hand controls, laptop fan mount, wireless and hard case. | ADX13: 1 | ADY13: 1 | ADZ13: 1 | AEA13: 1 | AEB13: 1 | AEC13: 1 | AEE13: 1 | AEF13: 1 | AEG13: 1 | AEH13: Academies | AEI13: 3 | AEJ13: 2 | AEK13: 2 | AEM13: 1 | AEN13: 3 | AEO13: 4 | AES13: 1 | AET13: 1 | AFB13: 1 | AFC13: 1 | AFG13: 1 | AFH13: 1 | AFI13: 1 | AFJ13: 1 | AFK13: 1 | AFL13: 1 | AFM13: 1 | AFN13: 1 | AFO13: 1 | AFP13: 1 | AFR13: 1 | AFX13: 1 | AFY13: 1 | AFZ13: 1 | AGA13: 2 | AGB13: 3 | AGC13: 1 | AGD13: 1 | AGE13: 1 | AGF13: 3 | AGG13: 3 | AGI13: 3 | AGN13: 1 | AGO13: 1 | AGP13: 61 | AGQ13: 2 | AHH13: 1 | AHI13: We are in the 3rd year of a National Center grant for closing the nationwide cybersecurity workforce shortage gap. The nationwide shortage gap still exists and thus center program resources still needed. The next grant proposal for an additional 5-years will strategically evolve and expand on the most pivotal and impactful products and services. | AHN13: 1 | AHO13: =OR($YH13=1,$YC13=1,$XV13=1,$SC13=1,$RO13=1,$QE13=1,$PM13=1,$OV13=1,$OS13=1,$OG13=1,$ME13=1,$LT13=1,$LL13=1,$JQ13=1,$JP13=1,$JG13=1,$FI13=1,$BH13=1) -> TRUE | AHP13: =AND($YH13=2,$YC13=2,$XV13=2,$SC13=2,$RO13=2,$QE13=2,$PM13=2,$OV13=2,$OS13=2,$OG13=2,$ME13=2,$LT13=2,$LL13=2,$JQ13=2,$JP13=2,$JG13=2,$FI13=2,$BH13=2) -> FALSE | AHQ13: =AND($YH13=3,$YC13=3,$XV13=3,$SC13=3,$RO13=3,$QE13=3,$PM13=3,$OV13=3,$OS13=3,$OG13=3,$ME13=3,$LT13=3,$LL13=3,$JQ13=3,$JP13=3,$JG13=3,$FI13=3,$BH13=3) -> FALSE
A14: 2400347 | B14: Waubonsee Water Ways: Building Pathways to Careers in the Water Sector | C14: 2 | D14: 0 | E14: 1 | F14: 2 | G14: 1 | H14: 2 | J14: 1 | K14: 1 | T14: =COUNTIF(K14:S14,1) -> 1 | U14: https://www.waubonsee.edu/programs-courses/programs-subject/science-mathematics-and-engineering/waubonsee-water-ways-building-pathways-careers-water-sector | V14: 3 | W14: 350000 | X14: 12 | AF14: 2 | AG14: 1 | AH14: 12 | AP14: 2 | AQ14: 1 | AR14: 3 | AS14: 1 | AT14: 1 | AU14: 1 | AV14: 1 | AW14: 1 | AX14: 1 | AY14: 1 | AZ14: 1 | BA14: 2 | BB14: 2 | BD14: 2 | BE14: 2 | BG14: 4 | BH14: 3 | FI14: 3 | JG14: 2 | JP14: 3 | JQ14: 2 | LL14: 3 | LT14: 2 | ME14: 3 | OG14: 3 | OS14: 2 | OV14: 2 | PM14: 3 | PN14: 1 | QA14: Light electric Vehicle Training (LEVA) was offered to 60+ students this is an obtainable industry recognized cert that serves as a feeder into entry-level jobs and 2 year programs | QB14: 1 | QC14: 1 | QD14: LEVA | QE14: 3 | RO14: 2 | SC14: 2 | XV14: 3 | YC14: 2 | YH14: 2 | YV14: 10 | YW14: 1 | YX14: 0 | YY14: 0 | YZ14: 0 | ZA14: 1 | ZC14: 0 | ZE14: 1 | ZF14: 1 | ZG14: 3 | ZH14: 2 | ZI14: 1 | ZJ14: 2 | ZK14: 2 | ZL14: 3 | ZM14: 1 | ZN14: 0 | ZO14: 0 | ZT14: 2 | ZU14: 1 | ZV14: 1 | ZW14: 3 | ZX14: 3 | AAA14: 1 | AAG14: 1 | AAH14: Helped us use the partnership rubric to evaluate the BILT effectively | AAI14: 1 | AAK14: 1 | AAO14: 4 | AAP14: 1 | AAQ14: 1 | AAR14: 1 | AAS14: 1 | AAT14: 2 | AAU14: 2 | AAV14: 1 | AAY14: 4 | ABC14: Having the evaluator help guide & troubleshoot the thinking process and modify our outputs. | ABD14: 3 | ABG14: Because they helped us think through the process and intentionally find creative ways to work through our situations. | ABI14: RUCKS Group | ABJ14: lrucks@rucksgroup.com | ABK14: RUCKS Group | ABL14: 2 | ABY14: 1 | ABZ14: 2 | ACA14: 1 | ACC14: Assembly of the BILT professionals who have contributed extensively to validating the KSAs needed for creating the certificate. | ACD14: 1 | ACE14: Qualitative and Quantitative Survey on the BILT engagement | ACF14: Assembly of the BILT professionals who have contributed extensively to validating the KSAs needed for creating the certificate. | ACG14: 1 | ADC14: 1 | ADD14: 1 | ADE14: 1 | ADG14: 1 | ADJ14: 1 | ADK14: 1 | ADL14: 4 | ADN14: 4 | ADU14: 1 | ADX14: 1 | ADY14: 2 | ADZ14: 1 | AEA14: 1 | AEB14: 1 | AEC14: 1 | AEE14: 1 | AEI14: 2 | AEJ14: 2 | AEK14: 2 | AEM14: 2 | AES14: 1 | AET14: 1 | AFB14: 3 | AFC14: 2 | AFJ14: 1 | AFL14: 1 | AFP14: 1 | AGA14: 1 | AGC14: 1 | AGG14: 1 | AGN14: 1 | AGO14: 1 | AGP14: 49 | AGQ14: 1 | AGR14: 1 | AGW14: 1 | AGX14: 1 | AHA14: 1 | AHG14: 2 | AHH14: 2 | AHJ14: Baed upon decision of home institution | AHN14: 2 | AHO14: =OR($YH14=1,$YC14=1,$XV14=1,$SC14=1,$RO14=1,$QE14=1,$PM14=1,$OV14=1,$OS14=1,$OG14=1,$ME14=1,$LT14=1,$LL14=1,$JQ14=1,$JP14=1,$JG14=1,$FI14=1,$BH14=1) -> FALSE | AHP14: =AND($YH14=2,$YC14=2,$XV14=2,$SC14=2,$RO14=2,$QE14=2,$PM14=2,$OV14=2,$OS14=2,$OG14=2,$ME14=2,$LT14=2,$LL14=2,$JQ14=2,$JP14=2,$JG14=2,$FI14=2,$BH14=2) -> FALSE | AHQ14: =AND($YH14=3,$YC14=3,$XV14=3,$SC14=3,$RO14=3,$QE14=3,$PM14=3,$OV14=3,$OS14=3,$OG14=3,$ME14=3,$LT14=3,$LL14=3,$JQ14=3,$JP14=3,$JG14=3,$FI14=3,$BH14=3) -> FALSE
A15: 2202225 | B15: Workforce for Water | C15: 10 | D15: 0 | E15: 2 | F15: 0 | G15: 1 | H15: 5 | I15: UH Maui College is accredited by WASC as a 4-year college/university but has only one bachelor's degree program - all other programs are 2-year programs; the college is a part of the University of Hawaii Community College system; additionally we hold the following designations: Tribal College Asian American, Native American, Pacific Islander Native Hawaiian | T15: =COUNTIF(K15:S15,1) -> 0 | U15: https://maui.hawaii.edu/programs/owtss | V15: 3 | W15: 1153803 | X15: 12 | AF15: 2 | AG15: 1 | AH15: 12 | AP15: 2 | AQ15: 2 | BA15: 2 | BB15: 6 | BD15: 6 | BE15: 2 | BG15: 4 | BH15: 1 | CD15: 9 | CE15: 0 | CF15: 0 | CG15: 0 | CI15: 0 | CJ15: 2 | CK15: 0 | CL15: 0 | CN15: 0 | CO15: 6 | CP15: 1 | CQ15: 2 | CR15: 6 | CS15: 0 | CT15: 1 | CV15: 0 | CW15: 0 | CX15: 0 | CY15: 0 | DA15: 0 | DB15: 0 | DC15: 0 | DD15: 0 | DE15: 0 | DF15: 0 | DG15: 0 | DI15: 0 | DJ15: 0 | DK15: 0 | DL15: 0 | DN15: 0 | DO15: 0 | DP15: 0 | DQ15: 0 | DR15: 0 | DS15: 0 | DT15: 0 | DV15: 0 | DW15: 0 | DX15: 0 | DY15: 0 | EA15: 0 | EB15: 0 | EC15: 0 | ED15: 0 | EE15: 0 | EF15: 0 | EG15: 0 | FA15: 0 | FB15: 0 | FC15: 0 | FD15: 0 | FG15: 1 | FH15: 0 | FI15: 1 | FJ15: 10 | HS15: 0 | HT15: 6 | HU15: 0 | HV15: 3 | HW15: 0 | JG15: 2 | JP15: 2 | JQ15: 2 | LL15: 2 | LT15: 2 | ME15: 1 | MF15: 1 | MG15: 2 | MH15: 2 | MI15: 2 | MJ15: 2 | MK15: 2 | ML15: 2 | NY15: 9 | OG15: 2 | OS15: 2 | OV15: 2 | PM15: 3 | PN15: 1 | QA15: National Institute for Automotive Service Excellence Certifications: xEV Industry Standards Level 1 and Level 2 xEV Electrical Safety Awareness Level 1 xEV Technician Electrical Safety Certification Level 2 | QB15: 1 | QC15: 3 | QE15: 2 | RO15: 2 | SC15: 2 | XV15: 2 | YC15: 2 | YH15: 2 | YV15: 13 | YW15: 1 | YX15: 4 | YY15: 3 | YZ15: 2 | ZA15: 1 | ZE15: 1 | ZF15: 1 | ZG15: 3 | ZH15: 2 | ZI15: 1 | ZJ15: 1 | ZK15: 2 | ZL15: 3 | ZM15: 1 | ZN15: 0 | ZO15: 1064 | ZP15: 1 | ZQ15: 2 | ZR15: 2 | ZT15: 3 | ZU15: 1 | ZV15: 1 | ZW15: 1 | ZX15: 1 | ZY15: 2 | AAA15: 1 | AAD15: 1 | AAF15: 1 | AAO15: 1 | AAP15: 2 | AAQ15: 1 | AAR15: 1 | AAS15: 4 | AAT15: 4 | AAU15: 2 | AAV15: 2 | AAW15: 4 | AAY15: 2 | ABA15: Our evaluator was incredibly busy - I think taking on too many projects - so therefore rarely available and quite scattered. | ABD15: 4 | ABH15: External evaluation is important for understanding if we are indeed reaching our goals. | ABI15: Summer Helms | ABJ15: summerhh70@gmail.com | ABK15: Summer Helms, Inc. | ABL15: 2 | ABY15: 3 | ABZ15: 2 | ACA15: 2 | ACC15: We completed the curriculum for and launched the Onsite Wastewater Treatment Systems Specialist Certificate at UH Maui College in August 2024. | ACD15: 1 | ACE15: We collected demographic data on our students, their performance during the first semester, and student evaluations. | ACF15: Industry Networking and Partnerships: We continue to cultivate strong partnerships with industry professionals, which have played a crucial role in enhancing our program. One of our key partners contributed as a consultant on curriculum refinement, ensuring that our courses align with industry standards and workforce needs. This collaboration also led to the partner taking on a lecturer position on campus, directly delivering the courses we developed. Additionally, our industry connections have created valuable experiential learning opportunities for students, allowing them to gain hands-on experience and practical insights that bridge the gap between education and real-world application. Recruitment: To recruit students for the OWTSS Certificate, we used a multi-faceted approach, using various outreach strategies to maximize engagement. Our Project Coordinator leads our recruitment. She attended multiple community meetings to connect directly with residents and stakeholders, providing information about cesspools, the new certificate program and its benefits. Social media advertising played a key role in reaching a broader audience, allowing us to target potential students effectively. Additionally, we leveraged outreach through a local media outlet to increase visibility and generate interest. We also recruited students from WAIʻs Work-4-Water class, an educational class about cesspools, their issues, and the conversion process. This allowed interested students to build upon their previous educational background and interests to continue this work and their education. These combined efforts helped to build awareness and drive enrollment, ensuring the program reached those who could benefit most from this opportunity, and resulted in students enrolling in the program. | ACG15: 1 | ADE15: 1 | ADF15: 1 | ADG15: 1 | ADL15: 2 | ADM15: 2 | ADN15: 2 | ADP15: 1 | ADS15: 1 | ADX15: 1 | ADY15: 2 | ADZ15: 1 | AEG15: 1 | AEH15: Workshop | AEO15: 1 | AFJ15: 1 | AGA15: 2 | AGN15: 2 | AGO15: 2 | AGP15: 100 | AGQ15: 2 | AHH15: 1 | AHI15: To maintain and develop the most up to date workforce training materials as we see advancements in emerging technologies in the E mobility industry and infrastructure. | AHN15: 1 | AHO15: =OR($YH15=1,$YC15=1,$XV15=1,$SC15=1,$RO15=1,$QE15=1,$PM15=1,$OV15=1,$OS15=1,$OG15=1,$ME15=1,$LT15=1,$LL15=1,$JQ15=1,$JP15=1,$JG15=1,$FI15=1,$BH15=1) -> TRUE | AHP15: =AND($YH15=2,$YC15=2,$XV15=2,$SC15=2,$RO15=2,$QE15=2,$PM15=2,$OV15=2,$OS15=2,$OG15=2,$ME15=2,$LT15=2,$LL15=2,$JQ15=2,$JP15=2,$JG15=2,$FI15=2,$BH15=2) -> FALSE | AHQ15: =AND($YH15=3,$YC15=3,$XV15=3,$SC15=3,$RO15=3,$QE15=3,$PM15=3,$OV15=3,$OS15=3,$OG15=3,$ME15=3,$LT15=3,$LL15=3,$JQ15=3,$JP15=3,$JG15=3,$FI15=3,$BH15=3) -> FALSE
